{
    "SUGESTÃO": 601692,
    "Und_NAT": 32861,
    "ESCANEADO": 435489,
    "SEPARAÇÃO": {
        "SKU": [
            22402.0,
            22580.0,
            801389.0
        ],
        "DESCRIÇÃO": [
            "LOSARTANA 50MG EMG 30",
            "NALDECON PACK 24'S",
            "INTEGRA CR LEI.N CR AV"
        ],
        "SUGESTÃO": [
            708.0,
            5989.0,
            240.0
        ],
        "FATURADO": [
            427.0,
            4446.0,
            60.0
        ],
        "NAT": [
            253.0,
            136.0,
            120.0
        ]
    },
    "RESSUPRIMENTO": {
        "SKU": [
            24428.0,
            646912.0,
            58189.0
        ],
        "DESCRIÇÃO": [
            "*QUETIAP 25 TEG 30S-C1",
            "NEEDS ALCOOL 70% 50ML",
            "CIMELIDE 12'S"
        ],
        "SUGESTÃO": [
            1223.0,
            227.0,
            404.0
        ],
        "FATURADO": [
            730.0,
            8.0,
            168.0
        ],
        "NAT": [
            365.0,
            183.0,
            164.0
        ]
    },
    "SUJEIRA": {
        "SKU": [
            655975.0,
            149933.0,
            26663.0
        ],
        "DESCRIÇÃO": [
            "ALLEGRA PED 6MG 60ML",
            "FUROSEMI 40MG PDG 20'S",
            "AMOX+CLA 875 EMG 14S"
        ],
        "SUGESTÃO": [
            470.0,
            191.0,
            464.0
        ],
        "FATURADO": [
            81.0,
            0.0,
            298.0
        ],
        "NAT": [
            277.0,
            153.0,
            134.0
        ]
    },
    "DECANTING": {
        "SKU": [
            5148.0,
            269366.0,
            28235.0
        ],
        "DESCRIÇÃO": [
            "NEEDS PALITO MAD C/5",
            "LAVITAN MELATON MAR 90",
            "FLUIR 12MCG 30'S+INAL"
        ],
        "SUGESTÃO": [
            272.0,
            123.0,
            246.0
        ],
        "FATURADO": [
            0.0,
            5.0,
            47.0
        ],
        "NAT": [
            155.0,
            105.0,
            104.0
        ]
    },
    "ENTRADA": {
        "SKU": [
            77609.0,
            682371.0,
            1230113.0
        ],
        "DESCRIÇÃO": [
            "RISQUE GEL HIB ROSA",
            "ACNEZIL GEL SECAT 10G",
            "CARMED ENX BUC FIN MIN"
        ],
        "SUGESTÃO": [
            354.0,
            551.0,
            2772.0
        ],
        "FATURADO": [
            28.0,
            180.0,
            1245.0
        ],
        "NAT": [
            230.0,
            203.0,
            142.0
        ]
    },
    "OVER": {
        "SKU": [
            29795.0,
            175644.0,
            75568.0
        ],
        "DESCRIÇÃO": [
            "OSCAL 500MG 60'S",
            "SALLVE ESFOL ENZIM 70G",
            "TREZOR 5MG 60'S"
        ],
        "SUGESTÃO": [
            114.0,
            106.0,
            74.0
        ],
        "FATURADO": [
            13.0,
            4.0,
            0.0
        ],
        "NAT": [
            82.0,
            74.0,
            57.0
        ]
    },
    "DROP'S": {
        "SKU": [
            80378.0,
            44375.0,
            607729.0
        ],
        "DESCRIÇÃO": [
            "BOZZ ESP HIDRATA 190G",
            "LACRIBEL 15ML",
            "COLG CR LUMIN GLOW 70G"
        ],
        "SUGESTÃO": [
            123.0,
            174.0,
            88.0
        ],
        "FATURADO": [
            7.0,
            63.0,
            0.0
        ],
        "NAT": [
            81.0,
            72.0,
            65.0
        ]
    },
    "SALDO ZERO": {
        "SKU": [
            8218.0,
            514170.0,
            304326.0
        ],
        "DESCRIÇÃO": [
            "NUPILL CR HID PES 120G",
            "ONDIF 8MG 10'S",
            "GABALLON 60'S"
        ],
        "SUGESTÃO": [
            140.0,
            330.0,
            77.0
        ],
        "FATURADO": [
            6.0,
            189.0,
            0.0
        ],
        "NAT": [
            74.0,
            68.0,
            60.0
        ]
    },
    "HOLDING": {
        "SKU": [
            51556.0,
            6943.0,
            2171.0
        ],
        "DESCRIÇÃO": [
            "NORETIST+ESTR EUG 1SER",
            "UROCRAN 30'S",
            "ATENSINA 0,100MG 30'S"
        ],
        "SUGESTÃO": [
            200.0,
            114.0,
            73.0
        ],
        "FATURADO": [
            71.0,
            22.0,
            11.0
        ],
        "NAT": [
            82.0,
            63.0,
            59.0
        ]
    },
    "SUGESTÃO ACIMA DA CAP.": {
        "SKU": [
            77720.0,
            312477.0,
            28356.0
        ],
        "DESCRIÇÃO": [
            "PANTENE CR BAMBU 240",
            "DIPIRONA MONOIDRA 10'S",
            "DOVE CD RECON COMP 400"
        ],
        "SUGESTÃO": [
            313.0,
            336.0,
            179.0
        ],
        "FATURADO": [
            42.0,
            112.0,
            0.0
        ],
        "NAT": [
            207.0,
            150.0,
            114.0
        ]
    },
    "SALDO DISTRIBUIDO": {
        "SKU": [
            586935.0,
            74692.0,
            535595.0
        ],
        "DESCRIÇÃO": [
            "VULT BATOM ROSE",
            "CF+CAR+DICLO+PRC EUG15",
            "GILLETTE AP CORPO C/2"
        ],
        "SUGESTÃO": [
            204.0,
            210.0,
            215.0
        ],
        "FATURADO": [
            10.0,
            47.0,
            55.0
        ],
        "NAT": [
            145.0,
            106.0,
            64.0
        ]
    },
    "ABASTECIMENTO": {
        "SKU": [
            1184452.0,
            1229622.0,
            978637.0
        ],
        "DESCRIÇÃO": [
            "EUCERIN PURE GEL LIMPE",
            "PANTENE CP QUERAT 240G",
            "TRENTO COOKIE&CREM 26G"
        ],
        "SUGESTÃO": [
            912.0,
            924.0,
            132.0
        ],
        "FATURADO": [
            95.0,
            384.0,
            96.0
        ],
        "NAT": [
            311.0,
            70.0,
            36.0
        ]
    },
    "MÁQUINA": {
        "SKU": [
            348225.0,
            1015625.0,
            239481.0
        ],
        "DESCRIÇÃO": [
            "STUDEX BRINCO ZIRC M G",
            "FERROPURUM 20MG 5AMPOL",
            "VITASAY MELAT LARAN 90"
        ],
        "SUGESTÃO": [
            383.0,
            355.0,
            25.0
        ],
        "FATURADO": [
            0.0,
            136.0,
            3.0
        ],
        "NAT": [
            217.0,
            112.0,
            19.0
        ]
    },
    "INVENTÁRIO": {
        "SKU": [
            60475.0,
            33451.0,
            884911.0
        ],
        "DESCRIÇÃO": [
            "GLUCERNA SR CHOC C/4",
            "CLOPIDOGREL 75 RXG 28S",
            "CICATRIC PROT F50 MD"
        ],
        "SUGESTÃO": [
            153.0,
            50.0,
            92.0
        ],
        "FATURADO": [
            0.0,
            0.0,
            0.0
        ],
        "NAT": [
            134.0,
            24.0,
            20.0
        ]
    },
    "100% Ñ AT.": {
        "SKU": [
            266005.0,
            23592.0,
            9064.0
        ],
        "DESCRIÇÃO": [
            "DPREV CAL 2000UI 30'S",
            "ZEEL COMP C/10 AMPL 2",
            "BRITENS COL 2+5MG/5ML"
        ],
        "SUGESTÃO": [
            28.0,
            35.0,
            35.0
        ],
        "FATURADO": [
            0.0,
            0.0,
            0.0
        ],
        "NAT": [
            28.0,
            23.0,
            21.0
        ]
    },
    "MOVIMENTAÇÃO": {
        "SKU": [
            58745.0,
            8034.0
        ],
        "DESCRIÇÃO": [
            "APTAMIL SENS ACT 800G",
            "MACH 3 SENSITIVE L8P6"
        ],
        "SUGESTÃO": [
            727.0,
            116.0
        ],
        "FATURADO": [
            477.0,
            95.0
        ],
        "NAT": [
            116.0,
            17.0
        ]
    },
    "SUGESTÃO ACIMA DO SALDO": {
        "SKU": [
            29615.0
        ],
        "DESCRIÇÃO": [
            "PROBAK AP BARBEAR L7P5"
        ],
        "SUGESTÃO": [
            3.0
        ],
        "FATURADO": [
            2.0
        ],
        "NAT": [
            1.0
        ]
    },
    "100% ATENDIDO": {
        "SKU": [
            10187.0,
            57846.0,
            961726.0
        ],
        "DESCRIÇÃO": [
            "HUGG LENC HIG 96U",
            "MECLIN 50MG 15'S",
            "FINI CORAC CIT ZER 35G"
        ],
        "SUGESTÃO": [
            43.0,
            31.0,
            504.0
        ],
        "FATURADO": [
            28.0,
            20.0,
            312.0
        ],
        "NAT": [
            0.0,
            0.0,
            0.0
        ]
    },
    "PCP": {
        "SKU": [
            77720.0,
            312477.0,
            60475.0
        ],
        "DESCRIÇÃO": [
            "PANTENE CR BAMBU 240",
            "DIPIRONA MONOIDRA 10'S",
            "GLUCERNA SR CHOC C/4"
        ],
        "SUGESTÃO": [
            313.0,
            336.0,
            153.0
        ],
        "FATURADO": [
            42.0,
            112.0,
            0.0
        ],
        "NAT": [
            207.0,
            150.0,
            134.0
        ]
    },
    "PRODUÇÃO": {
        "SKU": [
            1184452.0,
            22402.0,
            149933.0
        ],
        "DESCRIÇÃO": [
            "EUCERIN PURE GEL LIMPE",
            "LOSARTANA 50MG EMG 30",
            "FUROSEMI 40MG PDG 20'S"
        ],
        "SUGESTÃO": [
            912.0,
            708.0,
            191.0
        ],
        "FATURADO": [
            95.0,
            427.0,
            0.0
        ],
        "NAT": [
            311.0,
            253.0,
            153.0
        ]
    },
    "INBOUND": {
        "SKU": [
            24428.0,
            655975.0,
            77609.0
        ],
        "DESCRIÇÃO": [
            "*QUETIAP 25 TEG 30S-C1",
            "ALLEGRA PED 6MG 60ML",
            "RISQUE GEL HIB ROSA"
        ],
        "SUGESTÃO": [
            1223.0,
            470.0,
            354.0
        ],
        "FATURADO": [
            730.0,
            81.0,
            28.0
        ],
        "NAT": [
            365.0,
            277.0,
            230.0
        ]
    },
    "Nat": {
        "SKU": [
            24428.0,
            1184452.0,
            655975.0,
            22402.0,
            77609.0,
            348225.0,
            77720.0,
            682371.0,
            646912.0,
            58189.0,
            5148.0,
            149933.0,
            312477.0,
            586935.0,
            1230113.0,
            22580.0,
            26663.0,
            60475.0,
            77770.0,
            72406.0,
            1144818.0,
            801389.0,
            14147.0,
            58745.0,
            1071998.0,
            28356.0,
            250642.0,
            1015625.0,
            74692.0,
            269366.0
        ],
        "DESCRIÇÃO": [
            "*QUETIAP 25 TEG 30S-C1",
            "EUCERIN PURE GEL LIMPE",
            "ALLEGRA PED 6MG 60ML",
            "LOSARTANA 50MG EMG 30",
            "RISQUE GEL HIB ROSA",
            "STUDEX BRINCO ZIRC M G",
            "PANTENE CR BAMBU 240",
            "ACNEZIL GEL SECAT 10G",
            "NEEDS ALCOOL 70% 50ML",
            "CIMELIDE 12'S",
            "NEEDS PALITO MAD C/5",
            "FUROSEMI 40MG PDG 20'S",
            "DIPIRONA MONOIDRA 10'S",
            "VULT BATOM ROSE",
            "CARMED ENX BUC FIN MIN",
            "NALDECON PACK 24'S",
            "AMOX+CLA 875 EMG 14S",
            "GLUCERNA SR CHOC C/4",
            "PREDNI 20MG EUG 10'S",
            "EMPROL XR 25MG 30'S",
            "REXONA DES R ON POW 2U",
            "INTEGRA CR LEI.N CR AV",
            "TADALAFIL 20MG EMG 2'S",
            "APTAMIL SENS ACT 800G",
            "OLLIE PROT ST F95 20",
            "DOVE CD RECON COMP 400",
            "NEEDS FT MP BG 1,2X4,5",
            "FERROPURUM 20MG 5AMPOL",
            "CF+CAR+DICLO+PRC EUG15",
            "LAVITAN MELATON MAR 90"
        ],
        "SUGESTÃO": [
            1223.0,
            912.0,
            470.0,
            708.0,
            354.0,
            383.0,
            313.0,
            551.0,
            227.0,
            404.0,
            272.0,
            191.0,
            336.0,
            204.0,
            2772.0,
            5989.0,
            464.0,
            153.0,
            313.0,
            557.0,
            208.0,
            240.0,
            238.0,
            727.0,
            600.0,
            179.0,
            201.0,
            355.0,
            210.0,
            123.0
        ],
        "FATURADO": [
            730.0,
            95.0,
            81.0,
            427.0,
            28.0,
            0.0,
            42.0,
            180.0,
            8.0,
            168.0,
            0.0,
            0.0,
            112.0,
            10.0,
            1245.0,
            4446.0,
            298.0,
            0.0,
            105.0,
            311.0,
            36.0,
            60.0,
            48.0,
            477.0,
            189.0,
            0.0,
            40.0,
            136.0,
            47.0,
            5.0
        ],
        "NAT": [
            365.0,
            311.0,
            277.0,
            253.0,
            230.0,
            217.0,
            207.0,
            203.0,
            183.0,
            164.0,
            155.0,
            153.0,
            150.0,
            145.0,
            142.0,
            136.0,
            134.0,
            134.0,
            126.0,
            124.0,
            120.0,
            120.0,
            117.0,
            116.0,
            115.0,
            114.0,
            112.0,
            112.0,
            106.0,
            105.0
        ]
    }
}