{
    "SUGESTÃO": 473915,
    "ESCANEADO": 449134,
    "NAT_GERAL": 17861,
    "GRAFICO": {
        "SEPARAÇÃO": {
            "07:30": 2.75,
            "08:30": 2.85,
            "09:30": 0.13,
            "10:30": 3.47,
            "11:30": 3.26,
            "12:30": 2.47,
            "13:30": 2.44,
            "14:30": 2.27,
            "15:30": 3.26,
            "16:40": 2.58,
            "16:50": 3.03,
            "17:00": 2.18,
            "17:10": 3.39,
            "FECHAMENTO": null
        },
        "RESSUPRIMENTO": {
            "07:30": 0.27,
            "08:30": 0.3,
            "09:30": 0.22,
            "10:30": 0.27,
            "11:30": 0.22,
            "12:30": 0.21,
            "13:30": 0.26,
            "14:30": 0.31,
            "15:30": 0.3,
            "16:40": 0.27,
            "16:50": 0.32,
            "17:00": 0.26,
            "17:10": 0.3,
            "FECHAMENTO": null
        },
        "OVER": {
            "07:30": 0.06,
            "08:30": 0.27,
            "09:30": 0.5,
            "10:30": 0.37,
            "11:30": 0.3,
            "12:30": 0.33,
            "13:30": 0.34,
            "14:30": 0.36,
            "15:30": 0.26,
            "16:40": 0.25,
            "16:50": 0.23,
            "17:00": 0.27,
            "17:10": 0.24,
            "FECHAMENTO": null
        },
        "HOLDING": {
            "07:30": 0.06,
            "08:30": 0.16,
            "09:30": 1.73,
            "10:30": 0.12,
            "11:30": 0.1,
            "12:30": 0.17,
            "13:30": 0.18,
            "14:30": 0.12,
            "15:30": 0.11,
            "16:40": 0.23,
            "16:50": 0.15,
            "17:00": 0.16,
            "17:10": 0.22,
            "FECHAMENTO": null
        },
        "DECANTING": {
            "07:30": 0.51,
            "08:30": 0.12,
            "09:30": 0.42,
            "10:30": 0.18,
            "11:30": 0.13,
            "12:30": 0.12,
            "13:30": 0.12,
            "14:30": 0.12,
            "15:30": 0.16,
            "16:40": 0.12,
            "16:50": 0.12,
            "17:00": 0.08,
            "17:10": 0.14,
            "FECHAMENTO": null
        },
        "SUGESTÃO ACIMA DO SALDO": {
            "07:30": 0.0,
            "08:30": 0.1,
            "09:30": 0.35,
            "10:30": 0.07,
            "11:30": 0.05,
            "12:30": 0.07,
            "13:30": 0.06,
            "14:30": 0.06,
            "15:30": 0.08,
            "16:40": 0.1,
            "16:50": 0.11,
            "17:00": 0.09,
            "17:10": 0.09,
            "FECHAMENTO": null
        },
        "VENCIDO": {
            "07:30": 0.0,
            "08:30": 0.06,
            "09:30": 0.24,
            "10:30": 0.07,
            "11:30": 0.06,
            "12:30": 0.05,
            "13:30": 0.04,
            "14:30": 0.05,
            "15:30": 0.04,
            "16:40": 0.07,
            "16:50": 0.07,
            "17:00": 0.07,
            "17:10": 0.07,
            "FECHAMENTO": null
        },
        "SUGESTÃO ACIMA DA CAP.": {
            "07:30": 0.12,
            "08:30": 0.06,
            "09:30": 0.13,
            "10:30": 0.03,
            "11:30": 0.03,
            "12:30": 0.03,
            "13:30": 0.02,
            "14:30": 0.03,
            "15:30": 0.03,
            "16:40": 0.02,
            "16:50": 0.02,
            "17:00": 0.02,
            "17:10": 0.01,
            "FECHAMENTO": null
        },
        "DROP'S": {
            "07:30": 0.15,
            "08:30": 0.03,
            "09:30": 0.13,
            "10:30": 0.04,
            "11:30": 0.03,
            "12:30": 0.04,
            "13:30": 0.03,
            "14:30": 0.03,
            "15:30": 0.02,
            "16:40": 0.08,
            "16:50": 0.08,
            "17:00": 0.09,
            "17:10": 0.1,
            "FECHAMENTO": null
        },
        "GEOGRÁFICO": {
            "07:30": 0.72,
            "08:30": 0.02,
            "09:30": 0.07,
            "10:30": 0.02,
            "11:30": 0.03,
            "12:30": 0.04,
            "13:30": 0.02,
            "14:30": 0.03,
            "15:30": 0.02,
            "16:40": 0.03,
            "16:50": 0.03,
            "17:00": 0.04,
            "17:10": 0.03,
            "FECHAMENTO": null
        },
        "ABASTECIMENTO": {
            "07:30": 0.0,
            "08:30": 0.01,
            "09:30": 0.04,
            "10:30": 0.01,
            "11:30": 0.01,
            "12:30": 0.01,
            "13:30": 0.01,
            "14:30": 0.01,
            "15:30": 0.01,
            "16:40": 0.0,
            "16:50": 0.0,
            "17:00": 0.0,
            "17:10": 0.0,
            "FECHAMENTO": null
        },
        "100% Ñ AT.": {
            "07:30": 0.0,
            "08:30": 0.0,
            "09:30": 0.02,
            "10:30": 0.0,
            "11:30": 0.0,
            "12:30": 0.0,
            "13:30": 0.0,
            "14:30": 0.0,
            "15:30": 0.0,
            "16:40": 0.0,
            "16:50": 0.0,
            "17:00": 0.0,
            "17:10": 0.0,
            "FECHAMENTO": null
        },
        "ENTRADA": {
            "07:30": 0.28,
            "08:30": 0.0,
            "09:30": 0.0,
            "10:30": 0.0,
            "11:30": 0.0,
            "12:30": 0.0,
            "13:30": 0.0,
            "14:30": 0.0,
            "15:30": 0.0,
            "16:40": 0.0,
            "16:50": 0.0,
            "17:00": 0.0,
            "17:10": 0.0,
            "FECHAMENTO": null
        },
        "SUJEIRA": {
            "07:30": 0.0,
            "08:30": 0.0,
            "09:30": 0.0,
            "10:30": 0.37,
            "11:30": 0.39,
            "12:30": 0.3,
            "13:30": 0.29,
            "14:30": 0.32,
            "15:30": 0.45,
            "16:40": 1.36,
            "16:50": 1.81,
            "17:00": 1.59,
            "17:10": 1.39,
            "FECHAMENTO": null
        },
        "SALDO ZERO": {
            "07:30": 0.0,
            "08:30": 0.0,
            "09:30": 0.0,
            "10:30": 0.07,
            "11:30": 0.1,
            "12:30": 0.09,
            "13:30": 0.09,
            "14:30": 0.12,
            "15:30": 0.11,
            "16:40": 0.16,
            "16:50": 0.17,
            "17:00": 0.15,
            "17:10": 0.15,
            "FECHAMENTO": null
        },
        "SALDO DISTRIBUIDO": {
            "07:30": 0.11,
            "08:30": 0.0,
            "09:30": 0.0,
            "10:30": 0.0,
            "11:30": 0.0,
            "12:30": 0.0,
            "13:30": 0.0,
            "14:30": 0.0,
            "15:30": 0.0,
            "16:40": 0.0,
            "16:50": 0.0,
            "17:00": 0.0,
            "17:10": 0.0,
            "FECHAMENTO": null
        },
        "MÁQUINA": {
            "07:30": 0.0,
            "08:30": 0.0,
            "09:30": 0.0,
            "10:30": 0.03,
            "11:30": 0.05,
            "12:30": 0.03,
            "13:30": 0.05,
            "14:30": 0.04,
            "15:30": 0.04,
            "16:40": 0.06,
            "16:50": 0.06,
            "17:00": 0.05,
            "17:10": 0.06,
            "FECHAMENTO": null
        },
        "MISTURADO": {
            "07:30": 0.0,
            "08:30": 0.0,
            "09:30": 0.0,
            "10:30": 0.0,
            "11:30": 0.0,
            "12:30": 0.0,
            "13:30": 0.0,
            "14:30": 0.0,
            "15:30": 0.0,
            "16:40": 0.0,
            "16:50": 0.0,
            "17:00": 0.0,
            "17:10": 0.0,
            "FECHAMENTO": null
        },
        "SEM SALDO": {
            "07:30": 0.0,
            "08:30": 0.0,
            "09:30": 0.0,
            "10:30": 0.0,
            "11:30": 0.0,
            "12:30": 0.0,
            "13:30": 0.0,
            "14:30": 0.0,
            "15:30": 0.0,
            "16:40": 0.0,
            "16:50": 0.0,
            "17:00": 0.0,
            "17:10": 0.0,
            "FECHAMENTO": null
        },
        "MOVIMENTAÇÃO": {
            "07:30": 0.0,
            "08:30": 0.0,
            "09:30": 0.0,
            "10:30": 0.03,
            "11:30": 0.03,
            "12:30": 0.03,
            "13:30": 0.03,
            "14:30": 0.03,
            "15:30": 0.03,
            "16:40": 0.02,
            "16:50": 0.02,
            "17:00": 0.02,
            "17:10": 0.02,
            "FECHAMENTO": null
        },
        "CADASTRO": {
            "07:30": 0.0,
            "08:30": 0.0,
            "09:30": 0.0,
            "10:30": 0.0,
            "11:30": 0.0,
            "12:30": 0.0,
            "13:30": 0.0,
            "14:30": 0.0,
            "15:30": 0.0,
            "16:40": 0.0,
            "16:50": 0.0,
            "17:00": 0.0,
            "17:10": 0.0,
            "FECHAMENTO": null
        },
        "DESVIO DE QUALIDADE": {
            "07:30": 0.0,
            "08:30": 0.0,
            "09:30": 0.0,
            "10:30": 0.0,
            "11:30": 0.0,
            "12:30": 0.0,
            "13:30": 0.0,
            "14:30": 0.0,
            "15:30": 0.0,
            "16:40": 0.0,
            "16:50": 0.0,
            "17:00": 0.0,
            "17:10": 0.0,
            "FECHAMENTO": null
        },
        "SISTEMA": {
            "07:30": 0.0,
            "08:30": 0.0,
            "09:30": 0.0,
            "10:30": 0.0,
            "11:30": 0.0,
            "12:30": 0.0,
            "13:30": 0.0,
            "14:30": 0.0,
            "15:30": 0.0,
            "16:40": 0.0,
            "16:50": 0.0,
            "17:00": 0.0,
            "17:10": 0.0,
            "FECHAMENTO": null
        },
        "RECEBIMENTO": {
            "07:30": 0.0,
            "08:30": 0.0,
            "09:30": 0.0,
            "10:30": 0.0,
            "11:30": 0.0,
            "12:30": 0.0,
            "13:30": 0.0,
            "14:30": 0.0,
            "15:30": 0.0,
            "16:40": 0.0,
            "16:50": 0.0,
            "17:00": 0.0,
            "17:10": 0.0,
            "FECHAMENTO": null
        },
        "NAT": {
            "07:30": 4.57,
            "08:30": 4.09,
            "09:30": 4.04,
            "10:30": 4.57,
            "11:30": 5.25,
            "12:30": 5.7,
            "13:30": 3.83,
            "14:30": 4.82,
            "15:30": 4.74,
            "16:40": 6.81,
            "16:50": 4.28,
            "17:00": 5.56,
            "17:10": 6.97,
            "FECHAMENTO": null
        },
        "INBOUND": {
            "07:30": 1.45,
            "08:30": 0.6,
            "09:30": 1.5,
            "10:30": 0.7,
            "11:30": 0.61,
            "12:30": 0.54,
            "13:30": 0.92,
            "14:30": 0.85,
            "15:30": 0.72,
            "16:40": 0.91,
            "16:50": 0.69,
            "17:00": 0.72,
            "17:10": 0.73,
            "FECHAMENTO": null
        },
        "PRODUÇÃO": {
            "07:30": 2.63,
            "08:30": 4.04,
            "09:30": 3.0,
            "10:30": 3.4,
            "11:30": 2.9,
            "12:30": 3.31,
            "13:30": 3.79,
            "14:30": 2.68,
            "15:30": 3.03,
            "16:40": 4.46,
            "16:50": 4.29,
            "17:00": 4.99,
            "17:10": 2.97,
            "FECHAMENTO": null
        },
        "PCP": {
            "07:30": 0.82,
            "08:30": 0.61,
            "09:30": 0.56,
            "10:30": 0.55,
            "11:30": 0.54,
            "12:30": 0.33,
            "13:30": 0.35,
            "14:30": 0.32,
            "15:30": 0.43,
            "16:40": 0.41,
            "16:50": 0.48,
            "17:00": 0.4,
            "17:10": 0.38,
            "FECHAMENTO": null
        },
        "OUTROS": {
            "07:30": 0.0,
            "08:30": 0.0,
            "09:30": 0.0,
            "10:30": 0.0,
            "11:30": 0.0,
            "12:30": 0.0,
            "13:30": 0.0,
            "14:30": 0.0,
            "15:30": 0.0,
            "16:40": 0.0,
            "16:50": 0.0,
            "17:00": 0.0,
            "17:10": 0.0,
            "FECHAMENTO": null
        },
        "META": {
            "SEPARAÇÃO": 2.33,
            "ENTRADA": 0.16,
            "SUJEIRA": 1,
            "DECANTING": 0.37,
            "SALDO ZERO": 0.63,
            "RESSUPRIMENTO": 0.92,
            "HOLDING": 0.28,
            "DROP'S": 0.25,
            "OVER": 0.43,
            "MÁQUINA": 0,
            "ABASTECIMENTO": 0.05,
            "SALDO DISTRIBUIDO": 0,
            "MISTURADO": 0,
            "INVENTÁRIO": 0,
            "SUGESTÃO ACIMA DA CAP.": 0.24,
            "SUGESTÃO ACIMA DO SALDO": 0,
            "100% Ñ AT.": 0,
            "MOVIMENTAÇÃO": 0,
            "CADASTRO": 0,
            "SEM SALDO": 0,
            "DESVIO DE QUALIDADE": 0,
            "SISTEMA": 0,
            "VENCIDO": 0,
            "RECEBIMENTO": 0,
            "PRODUÇÃO": 2.98,
            "INBOUND": 2.15,
            "PCP": 1,
            "OUTROS": 0
        }
    },
    "TOP3": {
        "SEPARAÇÃO": {
            "SKU": [
                68665.81,
                42191.5,
                37756.74
            ],
            "DESCRIÇÃO": [
                "CIMELIDE 12'S",
                "VALDA FRIE CANELA 25G",
                "FIASP FLEXTOU 100U 3ML"
            ],
            "SUGESTÃO": [
                859.61,
                193.15,
                445.06
            ],
            "FATURADO": [
                582.65,
                182.81,
                0.0
            ],
            "NAT": [
                94.44,
                129.36,
                95.35
            ]
        },
        "SUJEIRA": {
            "SKU": [
                63239.1,
                294707.62,
                31543.01
            ],
            "DESCRIÇÃO": [
                "PREDNISOL 20MG EMG 10S",
                "VALSARTA 160MG CIG 30S (var)",
                "REACH FIO D MENT 50"
            ],
            "SUGESTÃO": [
                436.71,
                116.72,
                190.18
            ],
            "FATURADO": [
                318.04,
                0.0,
                146.37
            ],
            "NAT": [
                158.22,
                102.15,
                93.26
            ]
        },
        "DECANTING": {
            "SKU": [
                509151.73,
                1112885.27,
                123346.98
            ],
            "DESCRIÇÃO": [
                "NEEDS POL CAB E UNH 60",
                "FOREV LISS MASC B.VERN",
                "SENSOD CR REPAIR 2X100 (var)"
            ],
            "SUGESTÃO": [
                50.78,
                91.8,
                109.35
            ],
            "FATURADO": [
                17.23,
                0.0,
                36.1
            ],
            "NAT": [
                47.2,
                56.78,
                39.88
            ]
        },
        "RESSUPRIMENTO": {
            "SKU": [
                24302.36,
                70305.93,
                12521.88
            ],
            "DESCRIÇÃO": [
                "*SERTRALI 50 CIG 30-C1",
                "ANASTROZOL 1EUG 30'S (var)",
                "COLG CR DENT ORTHOG 90"
            ],
            "SUGESTÃO": [
                454.89,
                136.3,
                83.25
            ],
            "FATURADO": [
                314.84,
                58.04,
                0.0
            ],
            "NAT": [
                53.64,
                73.88,
                88.74
            ]
        },
        "MÁQUINA": {
            "SKU": [
                32422.15,
                943104.16,
                31297.48
            ],
            "DESCRIÇÃO": [
                "MIOSAN CAF 10/60MG 15S",
                "ELSEVEÂ ACÂ GLYCOL 200ML",
                "METOPROLOL 50MG NQG 30"
            ],
            "SUGESTÃO": [
                137.18,
                51.45,
                121.53
            ],
            "FATURADO": [
                79.64,
                0.0,
                63.03
            ],
            "NAT": [
                33.3,
                36.86,
                34.52
            ]
        },
        "SALDO ZERO": {
            "SKU": [
                95799.02,
                762856.57,
                979636.36
            ],
            "DESCRIÇÃO": [
                "TREZETE 10+10MG 30'S",
                "PREDSIM 20MG 20'S",
                "BWELL VIT C LB 500MG30"
            ],
            "SUGESTÃO": [
                149.72,
                70.69,
                158.45
            ],
            "FATURADO": [
                53.46,
                20.71,
                62.01
            ],
            "NAT": [
                74.07,
                86.79,
                57.37
            ]
        },
        "SUGESTÃO ACIMA DO SALDO": {
            "SKU": [
                56293.23,
                654335.95,
                62435.57
            ],
            "DESCRIÇÃO": [
                "OZEMPIC 1MG 4AGULHAS",
                "BIORE UV F50 A/RICH 70",
                "NUVARING ANEL VAG 1 UN"
            ],
            "SUGESTÃO": [
                374.37,
                132.34,
                247.17
            ],
            "FATURADO": [
                133.84,
                86.58,
                95.37
            ],
            "NAT": [
                44.07,
                112.27,
                57.23
            ]
        },
        "ABASTECIMENTO": {
            "SKU": [
                68191.29
            ],
            "DESCRIÇÃO": [
                "ATORVAST 40MG EMG 30'S"
            ],
            "SUGESTÃO": [
                595.37
            ],
            "FATURADO": [
                374.04
            ],
            "NAT": [
                1.23
            ]
        },
        "OVER": {
            "SKU": [
                23458.55,
                96498.74,
                29863.14
            ],
            "DESCRIÇÃO": [
                "MYLANTA PLUS MOR 240ML",
                "NEOSALDINA 15ML GTA",
                "KELTRINA PL 5% LC 60ML"
            ],
            "SUGESTÃO": [
                95.78,
                292.25,
                84.42
            ],
            "FATURADO": [
                108.43,
                23.7,
                18.43
            ],
            "NAT": [
                73.8,
                59.64,
                36.48
            ]
        },
        "DROP'S": {
            "SKU": [
                6904.24,
                20091.3,
                143692.24
            ],
            "DESCRIÇÃO": [
                "DAONIL 30'S",
                "LISTERINE A TART 250ML",
                "NEEDS MASC DESC INF 5U"
            ],
            "SUGESTÃO": [
                169.21,
                106.51,
                85.59
            ],
            "FATURADO": [
                48.09,
                0.0,
                22.65
            ],
            "NAT": [
                78.9,
                50.5,
                39.99
            ]
        },
        "HOLDING": {
            "SKU": [
                53713.62,
                105186.88,
                40785.33
            ],
            "DESCRIÇÃO": [
                "RISQUE CARE COB BR 8ML",
                "BITUFO ESC CLASS ORTO (var)",
                "STANGLIT 30 MG 60'S"
            ],
            "SUGESTÃO": [
                128.76,
                122.48,
                63.58
            ],
            "FATURADO": [
                0.0,
                63.36,
                11.23
            ],
            "NAT": [
                75.7,
                67.98,
                39.68
            ]
        },
        "SUGESTÃO ACIMA DA CAP.": {
            "SKU": [
                344807.39,
                589841.06
            ],
            "DESCRIÇÃO": [
                "EPISOL ACQUA F60 60ML",
                "NEEDS ENX ZERO MEN 500"
            ],
            "SUGESTÃO": [
                192.77,
                112.87
            ],
            "FATURADO": [
                0.0,
                104.28
            ],
            "NAT": [
                81.97,
                0.73
            ]
        },
        "GEOGRÁFICO": {
            "SKU": [
                64866.89,
                987299.36,
                545343.4
            ],
            "DESCRIÇÃO": [
                "LRP EFF GEL ALT TOL 60",
                "M.BONI ESC OVAL COCONU",
                "NEUTR NORW HD C/FR 400"
            ],
            "SUGESTÃO": [
                78.33,
                43.95,
                44.96
            ],
            "FATURADO": [
                0.0,
                0.0,
                13.78
            ],
            "NAT": [
                88.51,
                31.17,
                11.79
            ]
        },
        "MOVIMENTAÇÃO": {
            "SKU": [
                136216.32,
                158233.71
            ],
            "DESCRIÇÃO": [
                "APTANUTRI PROF 3 800G",
                "NANLAC SUPREME 1+ 800G"
            ],
            "SUGESTÃO": [
                118.18,
                155.43
            ],
            "FATURADO": [
                115.71,
                98.38
            ],
            "NAT": [
                48.55,
                37.53
            ]
        },
        "SALDO DISTRIBUIDO": {
            "SKU": [
                408404.67
            ],
            "DESCRIÇÃO": [
                "PANTOGAR SILICIO 30UN (var)"
            ],
            "SUGESTÃO": [
                10.71
            ],
            "FATURADO": [
                5.86
            ],
            "NAT": [
                4.3
            ]
        },
        "VENCIDO": {
            "SKU": [
                12688.94
            ],
            "DESCRIÇÃO": [
                "NEOLEFRIN 20'S"
            ],
            "SUGESTÃO": [
                228.68
            ],
            "FATURADO": [
                0.0
            ],
            "NAT": [
                211.61
            ]
        },
        "PRODUÇÃO": {
            "SKU": [
                11332.37,
                89438.88,
                45791.75
            ],
            "DESCRIÇÃO": [
                "NEOLEFRIN 20'S",
                "FIASP FLEXTOU 100U 3ML (var)",
                "VALDA FRIE CANELA 25G"
            ],
            "SUGESTÃO": [
                307.2,
                338.37,
                155.16
            ],
            "FATURADO": [
                0.0,
                0.0,
                271.53
            ],
            "NAT": [
                256.46,
                82.19,
                64.75
            ]
        },
        "INBOUND": {
            "SKU": [
                47140.86,
                249080.14,
                88017.78
            ],
            "DESCRIÇÃO": [
                "TREZETE 10+10MG 30'S",
                "VALSARTA 160MG CIG 30S",
                "RISQUE CARE COB BR 8ML (var)"
            ],
            "SUGESTÃO": [
                151.55,
                120.97,
                134.41
            ],
            "FATURADO": [
                0.0,
                30.21,
                0.0
            ],
            "NAT": [
                77.58,
                93.55,
                83.04
            ]
        },
        "PCP": {
            "SKU": [
                18992.57,
                31401.68,
                41569.7
            ],
            "DESCRIÇÃO": [
                "CIMELIDE 12'S",
                "PREDNISOL 20MG EMG 10S",
                "MYLANTA PLUS MOR 240ML"
            ],
            "SUGESTÃO": [
                774.0,
                231.04,
                696.49
            ],
            "FATURADO": [
                302.58,
                76.16,
                621.24
            ],
            "NAT": [
                150.99,
                73.35,
                129.39
            ]
        },
        "OUTROS": {
            "SKU": [
                36777.86,
                854108.96,
                76504.66
            ],
            "DESCRIÇÃO": [
                "OZEMPIC 1MG 4AGULHAS",
                "BIORE UV F50 A/RICH 70",
                "NUVARING ANEL VAG 1 UN"
            ],
            "SUGESTÃO": [
                195.33,
                152.69,
                438.31
            ],
            "FATURADO": [
                172.82,
                69.06,
                83.22
            ],
            "NAT": [
                88.59,
                54.24,
                44.25
            ]
        },
        "NAT": {
            "SKU": [
                9901.99,
                26218.6,
                56821.73
            ],
            "DESCRIÇÃO": [
                "PREDNISOL 20MG EMG 10S",
                "NEOLEFRIN 20'S",
                "TREZETE 10+10MG 30'S"
            ],
            "SUGESTÃO": [
                363.87,
                702.92,
                160.72
            ],
            "FATURADO": [
                0.0,
                487.56,
                42.25
            ],
            "NAT": [
                288.33,
                168.7,
                129.08
            ]
        }
    },
    "OFENSORES": {
        "1": "Unidades de SEPARAÇÃO: 11019",
        "2": "Unidades de RESSUPRIMENTO: 1160 (var)",
        "3": "Unidades de OVER: 1254",
        "PREVISÃO": "EM BREVE"
    },
    "NAT_POR_SETOR": {
        "07:30": {
            "M": 0.0,
            "V": 1.04,
            "Y": 0.0,
            "H": 1.58,
            "W": 0.29,
            "N": 0.07,
            "G": 0.0,
            "I": 0.0,
            "A": 0.03,
            "J": 0.83,
            "X": 0.04,
            "S": 0.0,
            "F": 0.0,
            "D": 0.4,
            "K": 0.11,
            "Z": 0.08,
            "L": 0.04,
            "O": 0.0,
            "C": 0.0,
            "T": 0.0,
            "U": 0.0,
            "B": 0.0,
            "R": 0.0
        },
        "08:30": {
            "M": 0.84,
            "V": 1.0,
            "Y": 0.66,
            "H": 0.5,
            "W": 0.15,
            "N": 0.02,
            "G": 0.0,
            "I": 0.0,
            "A": 0.31,
            "J": 0.0,
            "X": 0.36,
            "S": 0.0,
            "F": 0.0,
            "D": 0.13,
            "K": 0.13,
            "Z": 0.07,
            "L": 0.03,
            "O": 0.0,
            "C": 0.0,
            "T": 0.0,
            "U": 0.0,
            "B": 0.0,
            "R": 0.0
        },
        "09:30": {
            "M": 1.02,
            "V": 1.13,
            "Y": 0.57,
            "H": 0.73,
            "W": 0.06,
            "N": 0.02,
            "G": 0.01,
            "I": 0.0,
            "A": 0.24,
            "J": 0.15,
            "X": 0.04,
            "S": 0.0,
            "F": 0.0,
            "D": 0.2,
            "K": 0.07,
            "Z": 0.12,
            "L": 0.07,
            "O": 0.0,
            "C": 0.0,
            "T": 0.01,
            "U": 0.0,
            "B": 0.0,
            "R": 0.0
        },
        "10:30": {
            "M": 0.74,
            "V": 1.03,
            "Y": 0.82,
            "H": 0.65,
            "W": 0.14,
            "N": 0.02,
            "G": 0.0,
            "I": 0.0,
            "A": 0.35,
            "J": 0.0,
            "X": 0.35,
            "S": 0.0,
            "F": 0.0,
            "D": 0.18,
            "K": 0.08,
            "Z": 0.11,
            "L": 0.03,
            "O": 0.0,
            "C": 0.0,
            "T": 0.0,
            "U": 0.0,
            "B": 0.0,
            "R": 0.0
        },
        "11:30": {
            "M": 0.73,
            "V": 1.14,
            "Y": 1.01,
            "H": 0.53,
            "W": 0.09,
            "N": 0.02,
            "G": 0.0,
            "I": 0.0,
            "A": 0.32,
            "J": 0.0,
            "X": 0.36,
            "S": 0.0,
            "F": 0.0,
            "D": 0.14,
            "K": 0.08,
            "Z": 0.08,
            "L": 0.03,
            "O": 0.0,
            "C": 0.0,
            "T": 0.0,
            "U": 0.0,
            "B": 0.0,
            "R": 0.0
        },
        "12:30": {
            "M": 1.28,
            "V": 1.33,
            "Y": 0.74,
            "H": 0.48,
            "W": 0.1,
            "N": 0.02,
            "G": 0.0,
            "I": 0.0,
            "A": 0.26,
            "J": 0.0,
            "X": 0.21,
            "S": 0.0,
            "F": 0.0,
            "D": 0.26,
            "K": 0.08,
            "Z": 0.06,
            "L": 0.02,
            "O": 0.0,
            "C": 0.0,
            "T": 0.0,
            "U": 0.0,
            "B": 0.0,
            "R": 0.0
        },
        "13:30": {
            "M": 1.35,
            "V": 1.15,
            "Y": 0.85,
            "H": 0.49,
            "W": 0.1,
            "N": 0.02,
            "G": 0.0,
            "I": 0.0,
            "A": 0.24,
            "J": 0.0,
            "X": 0.2,
            "S": 0.0,
            "F": 0.0,
            "D": 0.2,
            "K": 0.07,
            "Z": 0.07,
            "L": 0.03,
            "O": 0.0,
            "C": 0.0,
            "T": 0.0,
            "U": 0.0,
            "B": 0.0,
            "R": 0.0
        },
        "14:30": {
            "M": 1.09,
            "V": 1.08,
            "Y": 0.73,
            "H": 0.54,
            "W": 0.07,
            "N": 0.02,
            "G": 0.0,
            "I": 0.0,
            "A": 0.37,
            "J": 0.0,
            "X": 0.35,
            "S": 0.0,
            "F": 0.0,
            "D": 0.24,
            "K": 0.07,
            "Z": 0.08,
            "L": 0.02,
            "O": 0.0,
            "C": 0.0,
            "T": 0.0,
            "U": 0.0,
            "B": 0.0,
            "R": 0.0
        },
        "15:30": {
            "M": 1.07,
            "V": 1.07,
            "Y": 1.06,
            "H": 0.45,
            "W": 0.07,
            "N": 0.02,
            "G": 0.0,
            "I": 0.0,
            "A": 0.21,
            "J": 0.0,
            "X": 0.32,
            "S": 0.0,
            "F": 0.0,
            "D": 0.25,
            "K": 0.1,
            "Z": 0.1,
            "L": 0.03,
            "O": 0.0,
            "C": 0.0,
            "T": 0.0,
            "U": 0.0,
            "B": 0.0,
            "R": 0.0
        },
        "16:40": {
            "M": 1.51,
            "V": 1.38,
            "Y": 0.99,
            "H": 0.66,
            "W": 0.06,
            "N": 0.05,
            "G": 0.19,
            "I": 0.0,
            "A": 0.24,
            "J": 0.03,
            "X": 0.25,
            "S": 0.0,
            "F": 0.0,
            "D": 0.19,
            "K": 0.1,
            "Z": 0.08,
            "L": 0.02,
            "O": 0.0,
            "C": 0.0,
            "T": 0.0,
            "U": 0.0,
            "B": 0.0,
            "R": 0.0
        },
        "16:50": {
            "M": 1.54,
            "V": 1.21,
            "Y": 0.87,
            "H": 0.76,
            "W": 0.07,
            "N": 0.04,
            "G": 0.2,
            "I": 0.0,
            "A": 0.32,
            "J": 0.02,
            "X": 0.16,
            "S": 0.0,
            "F": 0.0,
            "D": 0.18,
            "K": 0.05,
            "Z": 0.13,
            "L": 0.01,
            "O": 0.0,
            "C": 0.0,
            "T": 0.0,
            "U": 0.0,
            "B": 0.0,
            "R": 0.0
        },
        "17:00": {
            "M": 1.19,
            "V": 1.29,
            "Y": 1.26,
            "H": 0.67,
            "W": 0.07,
            "N": 0.06,
            "G": 0.16,
            "I": 0.0,
            "A": 0.28,
            "J": 0.02,
            "X": 0.23,
            "S": 0.0,
            "F": 0.0,
            "D": 0.15,
            "K": 0.05,
            "Z": 0.08,
            "L": 0.03,
            "O": 0.0,
            "C": 0.0,
            "T": 0.0,
            "U": 0.0,
            "B": 0.0,
            "R": 0.0
        },
        "17:10": {
            "M": 1.01,
            "V": 1.41,
            "Y": 0.87,
            "H": 0.82,
            "W": 0.07,
            "N": 0.05,
            "G": 0.22,
            "I": 0.0,
            "A": 0.25,
            "J": 0.02,
            "X": 0.17,
            "S": 0.0,
            "F": 0.0,
            "D": 0.13,
            "K": 0.07,
            "Z": 0.14,
            "L": 0.02,
            "O": 0.0,
            "C": 0.0,
            "T": 0.0,
            "U": 0.0,
            "B": 0.0,
            "R": 0.0
        }
    },
    "OFENSORES_RESUMO": {
        "MAIORES": {
            "SKU": [
                14148.4,
                42913.29,
                78546.96,
                74299.23,
                21883.41,
                74705.68,
                221632.43,
                72119.41,
                51297.77,
                373965.8,
                40971.97,
                8275.83,
                64449.59,
                55481.22,
                747959.28,
                87385.74,
                422.08,
                10948.29,
                33879.16,
                33207.07,
                20772.37,
                101374.62,
                90222.32,
                22223.1,
                19996.69,
                22944.7,
                176005.2,
                17712.82,
                972066.17,
                20653.03
            ],
            "DESCRIÇÃO": [
                "MIOSAN 5MG 30'S",
                "NEEDS ENX ZERO MEN 500",
                "PREDNISOL 20MG EMG 10S",
                "DAONIL 30'S",
                "VALDA FRIE CANELA 25G",
                "XULTOPHY 3ML 1 APLIC",
                "OSCILLOC 200K C/6",
                "*FLUOXET 20 TEG 30S-C1",
                "REACH FIO D MENT 50",
                "*QUETIAP 25 TEG 30S-C1",
                "LANTUS SOLOSTAR 3ML",
                "TREZETE 10+10MG 30'S",
                "MYLANTA PLUS MOR 240ML",
                "VITERGAN ZINCO PL 30'S (var)",
                "DOVE SAB LQ SENS 250M",
                "FIASP FLEXTOU 100U 3ML",
                "NEEDS ESP IMP BG 1,2X3 (var)",
                "OZEMPIC 1MG 4AGULHAS",
                "ANASTROZOL 1EUG 30'S",
                "*SERTRALI 50 CIG 30-C1",
                "VALSARTA 160MG CIG 30S (var)",
                "NEOSALDINA 15ML GTA",
                "LISTERINE A TART 250ML",
                "NEOLEFRIN 20'S",
                "COLG CR DENT ORTHOG 90",
                "CIMELIDE 12'S",
                "PANTOPRAZOL 40MEG 14'S",
                "RISQUE GEL CREM LOOK F",
                "RISQUE CARE COB BR 8ML",
                "LRP EFF GEL ALT TOL 60"
            ],
            "SETOR": [
                "M (var)",
                "V",
                "A",
                "A (var)",
                "H (var)",
                "V",
                "M",
                "Y (var)",
                "G",
                "V",
                "H",
                "D",
                "V",
                "M (var)",
                "G",
                "A",
                "M",
                "V",
                "H",
                "M (var)",
                "H",
                "Y",
                "G",
                "H",
                "Y",
                "M",
                "W",
                "M",
                "G",
                "V"
            ],
            "ENDEREÇO": [
                "5-D-07-013-03 (var)",
                "7-V-06-007-03 (var)",
                "7-M-26-007-04",
                "6-G-01-006-03",
                "7-M-04-007-04",
                "7-M-17-007-03",
                "7-V-07-026-03",
                "7-H-03-016-05",
                "6-G-01-001-03 (var)",
                "7-Y-08-007-03",
                "6-W-09-005-03",
                "7-M-13-016-03",
                "7-V-19-019-05",
                "7-H-13-001-04",
                "7-H-17-019-06",
                "7-M-18-022-03",
                "7-V-01-011-01 (var)",
                "6-A-06-011-03",
                "6-A-11-031-04",
                "6-G-01-002-04",
                "6-A-13-011-03 (var)",
                "7-Y-17-002-04",
                "7-H-21-017-05",
                "7-V-32-021-03",
                "7-V-09-015-02",
                "6-G-01-005-02",
                "7-M-14-019-06",
                "7-M-11-017-04",
                "7-H-03-018-01",
                "7-Y-18-017-02"
            ],
            "SUGESTÃO TOTAL": [
                248.19,
                313.46,
                181.11,
                134.27,
                90.18,
                675.83,
                248.47,
                437.55,
                546.48,
                84.46,
                368.6,
                79.4,
                231.78,
                65.21,
                147.52,
                165.06,
                151.89,
                395.64,
                125.69,
                411.71,
                72.52,
                62.34,
                66.19,
                72.73,
                149.57,
                184.69,
                123.31,
                129.89,
                140.29,
                69.28
            ],
            "UNID. FATURADAS": [
                0.0,
                151.87,
                0.0,
                0.0,
                0.0,
                23.57,
                33.04,
                0.0,
                154.19,
                108.04,
                0.0,
                48.79,
                141.08,
                344.37,
                0.0,
                29.56,
                66.08,
                22.88,
                0.0,
                0.0,
                302.27,
                0.0,
                0.0,
                0.0,
                0.0,
                139.15,
                768.46,
                3.51,
                80.32,
                355.42
            ],
            "UNID. NAT": [
                185.89,
                130.62,
                88.36,
                107.4,
                88.77,
                110.2,
                122.87,
                111.06,
                96.55,
                89.29,
                114.85,
                99.95,
                66.47,
                58.81,
                68.58,
                60.47,
                85.07,
                78.72,
                64.14,
                53.81,
                62.89,
                58.79,
                80.43,
                75.26,
                77.28,
                72.02,
                55.79,
                64.79,
                77.1,
                48.82
            ],
            "SALDO INICIAL": [
                113.45,
                51.18,
                0.0,
                1.81,
                3645.68,
                489.94,
                263.11,
                591.84,
                189.62,
                1187.43,
                6882.47,
                115.55,
                13.97,
                1960.07,
                80.9,
                134.93,
                73.88,
                8540.82,
                86.81,
                406.66,
                23.87,
                127.56,
                18.16,
                343.83,
                573.87,
                92.92,
                23.03,
                819.3,
                75.62,
                89.18
            ],
            "SALDO CASE": [
                0.0,
                4161.81,
                0.0,
                0.0,
                526.06,
                547.27,
                13.88,
                0.0,
                0.0,
                0.0,
                0.0,
                296.36,
                23.67,
                449.85,
                388.03,
                177.33,
                51.85,
                0.0,
                0.0,
                0.0,
                0.0,
                71.55,
                0.0,
                0.0,
                0.0,
                0.0,
                471.82,
                262.99,
                0.0,
                102.58
            ],
            "STATUS NÃO ATENDIMENTO": [
                "SEPARAÇÃO",
                "OVER",
                "RESSUPRIMENTO",
                "SEPARAÇÃO",
                "OVER",
                "OVER",
                "HOLDING (var)",
                "HOLDING",
                "SUGESTÃO ACIMA DO SALDO",
                "SUGESTÃO ACIMA DA CAP.",
                "SEPARAÇÃO",
                "OVER",
                "SEPARAÇÃO",
                "SEPARAÇÃO",
                "OVER",
                "SEPARAÇÃO",
                "SEPARAÇÃO",
                "SEPARAÇÃO",
                "RESSUPRIMENTO (var)",
                "SEPARAÇÃO",
                "RESSUPRIMENTO",
                "RESSUPRIMENTO",
                "GEOGRÁFICO (var)",
                "SEPARAÇÃO",
                "RESSUPRIMENTO",
                "SEPARAÇÃO",
                "SEPARAÇÃO (var)",
                "OVER",
                "SEPARAÇÃO",
                "OVER"
            ],
            "STATUS VALIDADO": [
                "VENCIDO",
                "SUJEIRA",
                "SALDO ZERO",
                null,
                null,
                "SEPARAÇÃO",
                "SUJEIRA",
                null,
                null,
                null,
                null,
                "DROP'S",
                null,
                "SUJEIRA (var)",
                "SUJEIRA",
                "OVER",
                "SUJEIRA",
                "SUJEIRA",
                null,
                null,
                "SUJEIRA",
                null,
                null,
                "SUJEIRA",
                null,
                null,
                "SUJEIRA",
                "SUJEIRA",
                "SUJEIRA",
                "DROP'S"
            ],
            "SALDO ATIVO": [
                0.0,
                112.38,
                15.03,
                3005.19,
                106.62,
                218.77,
                68.31,
                129.13,
                0.0,
                1257.06,
                144.16,
                108.18,
                177.8,
                101.23,
                92.21,
                0.0,
                43.03,
                0.82,
                0.0,
                8132.44,
                16.94,
                310.66,
                12126.78,
                4526.75,
                437.83,
                9.65,
                1.74,
                310.28,
                0.0,
                139.3
            ],
            "QUEM VALIDOU": [
                "Luciana",
                "PAULA",
                "ESCANEAMENTO",
                "SEM VALIDAÇÃO",
                "SEM VALIDAÇÃO",
                "PAULA",
                "João",
                "SEM VALIDAÇÃO",
                "SEM VALIDAÇÃO",
                "SEM VALIDAÇÃO",
                "SEM VALIDAÇÃO",
                "Júlio (var)",
                "SEM VALIDAÇÃO (var)",
                "DEBORA",
                "Evandro",
                "Luiz",
                "CAIQUE",
                "TAINA",
                "SEM VALIDAÇÃO",
                "SEM VALIDAÇÃO (var)",
                "TAINA",
                "SEM VALIDAÇÃO",
                "SEM VALIDAÇÃO",
                "CAIQUE (var)",
                "SEM VALIDAÇÃO",
                "SEM VALIDAÇÃO (var)",
                "dennis",
                "Victoria",
                "GABRIEL",
                "PAULA"
            ],
            "DIAS RECORRENTE": [
                8.89,
                9.84,
                11.15,
                1.15,
                4.75,
                6.76,
                4.31,
                4.37,
                0.0,
                4.59,
                0.0,
                6.55,
                4.36,
                11.74,
                7.19,
                13.93,
                7.28,
                8.45,
                1.97,
                0.0,
                0.0,
                6.12,
                7.1,
                6.14,
                0.72,
                0.0,
                9.39,
                0.0,
                0.96,
                5.96
            ],
            "NAT ACUMULADO SKU": [
                29.12,
                99.85,
                158.5,
                2.59,
                9.65,
                25.82,
                13.12,
                385.66,
                0.0,
                5.95,
                0.0,
                40.94,
                5.95,
                254.21,
                19.38,
                22.01,
                12.08,
                16.74,
                9.71,
                0.0,
                0.0,
                22.16,
                13.41,
                126.04,
                1.03,
                0.0,
                441.03,
                0.0,
                348.66,
                7.7
            ]
        },
        "RESSUPRIMENTO": {
            "SKU": [
                98888.57,
                58399.22,
                299728.93,
                31.21,
                1439019.78,
                114939.65,
                730579.62,
                989107.95,
                5887.93,
                142854.17,
                23357.4,
                93492.37,
                576945.35,
                38113.8,
                18445.75,
                1246304.94,
                50102.23,
                20209.21,
                107889.24,
                194535.61,
                18889.13,
                63834.27,
                44079.29,
                110841.48,
                28274.84,
                54600.1,
                97396.38,
                267706.94,
                4388.48,
                1214924.34
            ],
            "DESCRIÇÃO": [
                "TREZETE 10+10MG 30'S (var)",
                "*SERTRALI 50 CIG 30-C1 (var)",
                "*QUETIAP 25 TEG 30S-C1",
                "COLG CR DENT ORTHOG 90",
                "ANASTROZOL 1EUG 30'S",
                "CIMEGRIPE 20'S",
                "AFTLIV SOL BUCAL 25ML",
                "COLG CREME XTREME L3P2",
                "SENSOD CR REPAIR 2X100",
                "APTANUTRI PROF 3 800G",
                "*TRILEPTAL 300MG 60-C1 (var)",
                "HUGG LENC RN 48UN",
                "FEMINIS 30'S",
                "NEEDS POL CAB E UNH 60",
                "IMEDIA TINT 5 47G (var)",
                "GRANADO SB BEB CAMOM90",
                "NANLAC SUPREME 1+ 800G (var)",
                "INTIM PROT S/P L80P60",
                "CLAVULIN 500+125MG 21S",
                "J&J BABY OLEO AMEN 200",
                "LEVANLOD 5MG BLG 30S",
                "DOVE SAB BRANC LMPM C6",
                "JONTEX PELE C/PELE 12 ",
                "*ARCOXIA 90MG 5'S-C1",
                "LUVIS GOLD 60 'S",
                "REVITALIFT ANT OL 49G",
                "ACEBROFIL 50MG EMG 120",
                "SENSIBIO H2O MIC 100ML",
                "NEEDS AG INSULINA 4MM",
                "BETAM+GENT EMS CR 30G"
            ],
            "SETOR": [
                "M",
                "A (var)",
                "A",
                "Y",
                "V",
                "D",
                "Y",
                "Y",
                "H",
                "W",
                "A",
                "N",
                "M",
                "M",
                "Y",
                "Y",
                "W",
                "Y",
                "X",
                "H (var)",
                "V",
                "Z",
                "H",
                "A",
                "M",
                "Y",
                "V",
                "H",
                "M (var)",
                "X"
            ],
            "ENDEREÇO": [
                "7-M-26-007-04",
                "6-A-11-031-04 (var)",
                "6-A-13-011-03 (var)",
                "7-Y-17-002-04",
                "7-V-09-015-02",
                "5-D-05-006-04",
                "7-Y-06-021-02",
                "7-Y-19-002-04 (var)",
                "7-H-22-001-03",
                "6-W-04-015-01",
                "6-A-09-013-06",
                "6-N-07-008-02",
                "7-M-27-020-02",
                "7-M-21-011-02",
                "7-Y-20-015-06",
                "7-Y-04-012-05 (var)",
                "6-W-07-011-01",
                "7-Y-27-003-02",
                "6-X-02-007-04",
                "7-H-30-026-04",
                "7-V-09-023-04",
                "5-Z-14-005-01",
                "7-H-24-014-04 (var)",
                "6-A-05-026-03 (var)",
                "7-M-13-021-06",
                "7-Y-02-019-04",
                "7-V-12-016-03",
                "7-H-22-011-03",
                "7-M-09-017-03 (var)",
                "6-X-03-014-05"
            ],
            "SUGESTÃO TOTAL": [
                177.85,
                306.12,
                429.9,
                175.68,
                91.33,
                2229.51,
                126.58,
                137.47,
                51.82,
                215.83,
                145.79,
                282.82,
                38.19,
                92.05,
                71.52,
                163.64,
                189.06,
                100.25,
                267.36,
                38.66,
                55.83,
                1080.84,
                40.58,
                33.2,
                51.21,
                40.85,
                33.4,
                25.92,
                75.25,
                35.64
            ],
            "UNID. FATURADAS": [
                44.11,
                347.16,
                384.24,
                61.75,
                0.0,
                2617.07,
                0.0,
                49.28,
                13.53,
                93.54,
                64.99,
                176.45,
                0.0,
                30.73,
                18.36,
                71.36,
                92.08,
                63.18,
                142.25,
                0.0,
                0.0,
                1159.07,
                10.14,
                0.0,
                22.17,
                0.0,
                8.75,
                6.25,
                23.34,
                9.19
            ],
            "UNID. NAT": [
                83.3,
                58.57,
                75.25,
                90.9,
                65.55,
                63.95,
                59.64,
                39.38,
                51.09,
                36.53,
                36.71,
                48.23,
                38.73,
                47.64,
                45.42,
                30.34,
                42.47,
                28.55,
                30.53,
                35.97,
                33.57,
                27.09,
                31.36,
                21.18,
                20.16,
                20.57,
                22.16,
                24.81,
                24.77,
                21.75
            ],
            "SALDO INICIAL": [
                61.03,
                421.83,
                258.22,
                16.15,
                16.41,
                54.38,
                15.83,
                110.23,
                25.1,
                228.32,
                128.4,
                20.31,
                103.69,
                30.66,
                5.01,
                36.74,
                94.83,
                35.34,
                3.91,
                2902.76,
                68.84,
                58.15,
                27.51,
                53.29,
                0.0,
                39.03,
                27.81,
                39.72,
                61.78,
                37.47
            ],
            "SALDO CASE": [
                0.0,
                0.0,
                0.0,
                85.43,
                0.0,
                0.0,
                0.0,
                0.0,
                0.0,
                0.0,
                0.0,
                0.0,
                0.0,
                26.65,
                12.42,
                0.0,
                0.0,
                58.59,
                0.0,
                0.0,
                0.0,
                0.0,
                0.0,
                0.0,
                22.29,
                0.0,
                0.0,
                6.0,
                0.0,
                0.0
            ],
            "STATUS NÃO ATENDIMENTO": [
                "RESSUPRIMENTO",
                "RESSUPRIMENTO",
                "RESSUPRIMENTO",
                "RESSUPRIMENTO",
                "RESSUPRIMENTO (var)",
                "RESSUPRIMENTO",
                "RESSUPRIMENTO",
                "RESSUPRIMENTO",
                "RESSUPRIMENTO",
                "RESSUPRIMENTO",
                "RESSUPRIMENTO",
                "RESSUPRIMENTO",
                "RESSUPRIMENTO",
                "RESSUPRIMENTO",
                "RESSUPRIMENTO",
                "RESSUPRIMENTO",
                "RESSUPRIMENTO",
                "RESSUPRIMENTO",
                "RESSUPRIMENTO",
                "RESSUPRIMENTO",
                "RESSUPRIMENTO",
                "RESSUPRIMENTO",
                "RESSUPRIMENTO (var)",
                "RESSUPRIMENTO (var)",
                "RESSUPRIMENTO",
                "RESSUPRIMENTO",
                "RESSUPRIMENTO",
                "RESSUPRIMENTO",
                "RESSUPRIMENTO",
                "RESSUPRIMENTO"
            ],
            "STATUS VALIDADO": [
                "SALDO ZERO",
                null,
                "SUJEIRA",
                null,
                null,
                "SEPARAÇÃO",
                "SUJEIRA",
                null,
                "DECANTING (var)",
                "MOVIMENTAÇÃO",
                "SUJEIRA",
                "RESSUPRIMENTO",
                "SUJEIRA",
                "DECANTING",
                "HOLDING",
                "DROP'S",
                "MOVIMENTAÇÃO",
                null,
                "SEPARAÇÃO (var)",
                "SUJEIRA",
                null,
                "SEPARAÇÃO",
                null,
                null,
                null,
                null,
                null,
                null,
                "SUJEIRA",
                null
            ],
            "SALDO ATIVO": [
                0.0,
                108.0,
                245.36,
                225.35,
                0.0,
                3000.36,
                46.01,
                74.46,
                1.01,
                308.91,
                280.95,
                214.14,
                5.89,
                45.04,
                4.85,
                52.76,
                67.85,
                0.94,
                78.35,
                30.08,
                42.43,
                227.29,
                15.22,
                22.88,
                7.32,
                4.44,
                1.25,
                7.52,
                11.71,
                47.9
            ],
            "QUEM VALIDOU": [
                "ESCANEAMENTO",
                "SEM VALIDAÇÃO",
                "TAINA",
                "SEM VALIDAÇÃO",
                "SEM VALIDAÇÃO",
                "Maria",
                "PAULA",
                "SEM VALIDAÇÃO",
                "Luiz",
                "Luiz",
                "TAINA",
                "TAINA",
                "PAULA",
                "Luiz",
                "PAULA",
                "PAULA",
                "TAINA (var)",
                "SEM VALIDAÇÃO",
                "Luiz (var)",
                "Luiz (var)",
                "SEM VALIDAÇÃO (var)",
                "Maria",
                "SEM VALIDAÇÃO",
                "SEM VALIDAÇÃO (var)",
                "SEM VALIDAÇÃO",
                "SEM VALIDAÇÃO",
                "SEM VALIDAÇÃO",
                "SEM VALIDAÇÃO (var)",
                "PAULA",
                "SEM VALIDAÇÃO"
            ],
            "DIAS RECORRENTE": [
                9.63,
                1.6,
                0.0,
                9.05,
                0.92,
                10.27,
                6.42,
                4.48,
                3.79,
                5.88,
                3.02,
                5.98,
                7.71,
                1.91,
                5.29,
                4.93,
                9.35,
                7.44,
                2.18,
                4.51,
                5.69,
                12.74,
                6.29,
                2.3,
                8.08,
                1.58,
                5.89,
                4.72,
                6.8,
                4.5
            ],
            "NAT ACUMULADO SKU": [
                110.44,
                9.57,
                0.0,
                20.72,
                0.86,
                201.17,
                63.93,
                4.67,
                32.72,
                56.58,
                7.69,
                9.05,
                69.57,
                6.86,
                12.31,
                46.92,
                111.16,
                11.63,
                22.79,
                44.18,
                61.65,
                97.12,
                39.21,
                1.68,
                58.58,
                2.39,
                32.87,
                94.86,
                21.59,
                58.24
            ]
        },
        "SEPARAÇÃO": {
            "SKU": [
                12839.36,
                68266.69,
                31089.47,
                58981.88,
                57896.17,
                85862.27,
                544.38,
                11654.41,
                37405.46,
                29961.84,
                20022.6,
                241106.9,
                1508062.79,
                47563.58,
                17593.22,
                54943.18,
                121042.63,
                36822.3,
                1130498.99,
                11846.25,
                1217074.89,
                16436.41,
                51312.2,
                103672.4,
                91474.13,
                22501.5,
                165464.38,
                117866.58,
                35839.75,
                570.39
            ],
            "DESCRIÇÃO": [
                "NEOLEFRIN 20'S",
                "FIASP FLEXTOU 100U 3ML",
                "VALDA FRIE CANELA 25G",
                "MIOSAN 5MG 30'S",
                "REACH FIO D MENT 50 (var)",
                "NEOSALDINA 15ML GTA",
                "PANTOPRAZOL 40MEG 14'S",
                "*FLUOXET 20 TEG 30S-C1",
                "LANTUS SOLOSTAR 3ML",
                "OSCILLOC 200K C/6",
                "XULTOPHY 3ML 1 APLIC",
                "NEEDS ESP IMP BG 1,2X3",
                "RISQUE GEL CREM LOOK F",
                "CELESTAMINE S/AC 120ML",
                "AMOX BIG 500MG 30'S",
                "GILLETTE FUSION5 C/4UN",
                "LIDOCAINA 50MG PBG 25G",
                "LASTACAFT 0,25 3ML",
                "PREDSIM 20MG 20'S",
                "*DIVALCON ER 500MG 60S",
                "ENGOV AFTER P.LIMON250",
                "BB CR BASE MEDIA 30ML",
                "*RISPERID 3 EUG30'S",
                "NORIPURUM EV END 5X5ML",
                "SBP REP SUAV REF+50%SG",
                "ICACORT CREME 30GR",
                "DOVE DES MEN+CAR INVIS",
                "BETADINE XR 48MG 30'S",
                "STILGRIP 1X5G (var)",
                "ADVIL EXTR ALIVIO 20'S (var)"
            ],
            "SETOR": [
                "D",
                "G",
                "W",
                "V",
                "H",
                "M",
                "V",
                "A",
                "G (var)",
                "V",
                "G",
                "M",
                "H",
                "M",
                "X",
                "H",
                "V",
                "M",
                "M",
                "A (var)",
                "L",
                "Y",
                "A",
                "G",
                "Y (var)",
                "M",
                "N",
                "M",
                "J (var)",
                "M"
            ],
            "ENDEREÇO": [
                "5-D-07-013-03",
                "6-G-01-006-03",
                "6-W-09-005-03",
                "7-V-19-019-05",
                "7-H-13-001-04",
                "7-M-18-022-03 (var)",
                "7-V-01-011-01 (var)",
                "6-A-06-011-03",
                "6-G-01-002-04",
                "7-V-32-021-03",
                "6-G-01-005-02",
                "7-M-14-019-06",
                "7-H-03-018-01",
                "7-M-31-006-01",
                "6-X-03-026-03 (var)",
                "7-H-13-024-04",
                "7-V-01-016-01",
                "7-M-31-017-01",
                "7-M-19-013-06",
                "6-A-06-006-03",
                "5-L-03-024-01",
                "7-Y-30-014-01",
                "6-A-11-003-01",
                "6-G-01-001-02",
                "7-Y-03-005-03",
                "7-M-05-005-02",
                "6-N-06-004-01",
                "7-M-17-018-04",
                "6-J-01-005-02",
                "7-M-09-003-03"
            ],
            "SUGESTÃO TOTAL": [
                273.04,
                328.78,
                177.31,
                114.72,
                208.69,
                144.85,
                113.38,
                93.06,
                295.62,
                103.99,
                190.04,
                87.63,
                57.73,
                117.68,
                61.99,
                73.79,
                84.85,
                144.02,
                78.57,
                71.5,
                46.64,
                107.99,
                94.19,
                248.65,
                110.52,
                123.6,
                177.72,
                63.59,
                662.03,
                40.91
            ],
            "UNID. FATURADAS": [
                0.0,
                166.25,
                0.0,
                0.0,
                107.01,
                21.46,
                28.31,
                0.0,
                125.89,
                0.0,
                117.73,
                23.69,
                0.0,
                45.05,
                0.0,
                0.0,
                0.0,
                46.98,
                18.57,
                0.0,
                0.0,
                0.0,
                0.0,
                111.73,
                0.0,
                96.28,
                117.2,
                2.76,
                696.46,
                0.0
            ],
            "UNID. NAT": [
                186.56,
                77.46,
                104.85,
                80.36,
                67.54,
                76.24,
                76.39,
                92.64,
                52.62,
                61.95,
                47.75,
                59.65,
                50.61,
                68.79,
                77.95,
                46.46,
                70.99,
                68.97,
                69.29,
                41.59,
                64.63,
                55.48,
                61.64,
                38.7,
                56.24,
                48.53,
                63.17,
                52.59,
                42.68,
                63.6
            ],
            "SALDO INICIAL": [
                913.2,
                6620.1,
                869.41,
                145.44,
                768.6,
                121.65,
                472.56,
                1598.8,
                11473.93,
                345.54,
                5780.16,
                151.88,
                163.99,
                99.98,
                118.58,
                111.88,
                109.94,
                252.2,
                82.6,
                595.22,
                40.44,
                198.1,
                522.17,
                6319.2,
                452.96,
                586.22,
                408.08,
                143.66,
                1042.19,
                373.05
            ],
            "SALDO CASE": [
                508.73,
                149.44,
                0.0,
                0.0,
                0.0,
                0.0,
                0.0,
                1010.56,
                0.0,
                0.0,
                197.8,
                0.0,
                0.0,
                56.16,
                0.0,
                0.0,
                218.21,
                0.0,
                434.15,
                16.75,
                202.21,
                0.0,
                0.0,
                0.0,
                56.09,
                0.0,
                0.0,
                0.0,
                0.0,
                185.65
            ],
            "STATUS NÃO ATENDIMENTO": [
                "SEPARAÇÃO (var)",
                "SEPARAÇÃO",
                "SEPARAÇÃO",
                "SEPARAÇÃO",
                "SEPARAÇÃO",
                "SEPARAÇÃO",
                "SEPARAÇÃO",
                "SEPARAÇÃO",
                "SEPARAÇÃO (var)",
                "SEPARAÇÃO (var)",
                "SEPARAÇÃO",
                "SEPARAÇÃO",
                "SEPARAÇÃO",
                "SEPARAÇÃO",
                "SEPARAÇÃO",
                "SEPARAÇÃO",
                "SEPARAÇÃO",
                "SEPARAÇÃO",
                "SEPARAÇÃO (var)",
                "SEPARAÇÃO",
                "SEPARAÇÃO",
                "SEPARAÇÃO",
                "SEPARAÇÃO",
                "SEPARAÇÃO",
                "SEPARAÇÃO",
                "SEPARAÇÃO",
                "SEPARAÇÃO",
                "SEPARAÇÃO",
                "SEPARAÇÃO (var)",
                "SEPARAÇÃO"
            ],
            "STATUS VALIDADO": [
                "VENCIDO (var)",
                null,
                null,
                null,
                "SUJEIRA",
                "OVER (var)",
                "SUJEIRA (var)",
                "SUJEIRA (var)",
                null,
                "SUJEIRA",
                null,
                "SUJEIRA",
                "SUJEIRA",
                null,
                "SUJEIRA",
                "SUJEIRA",
                "SUJEIRA (var)",
                null,
                "SALDO ZERO",
                "SUJEIRA",
                null,
                null,
                null,
                null,
                "SUJEIRA",
                null,
                "SUJEIRA",
                "SUJEIRA",
                null,
                "SUJEIRA"
            ],
            "SALDO ATIVO": [
                199.9,
                4517.05,
                471.15,
                75.85,
                86.16,
                14.22,
                41.98,
                1149.01,
                8846.52,
                107.65,
                3535.11,
                229.19,
                236.41,
                42.76,
                206.25,
                40.21,
                126.65,
                132.03,
                44.5,
                107.39,
                60.73,
                153.11,
                274.51,
                4250.15,
                476.98,
                535.11,
                358.31,
                35.71,
                404.38,
                15.19
            ],
            "QUEM VALIDOU": [
                "Luciana",
                "SEM VALIDAÇÃO",
                "SEM VALIDAÇÃO",
                "SEM VALIDAÇÃO",
                "DEBORA",
                "Luiz",
                "CAIQUE",
                "TAINA",
                "SEM VALIDAÇÃO",
                "CAIQUE",
                "SEM VALIDAÇÃO",
                "dennis",
                "GABRIEL",
                "SEM VALIDAÇÃO",
                "Luiz",
                "PAULA",
                "CAIQUE (var)",
                "SEM VALIDAÇÃO",
                "ESCANEAMENTO",
                "TAINA",
                "SEM VALIDAÇÃO",
                "SEM VALIDAÇÃO",
                "SEM VALIDAÇÃO",
                "SEM VALIDAÇÃO",
                "REGIANE",
                "SEM VALIDAÇÃO",
                "TAINA",
                "PAULA JULIÃO (var)",
                "SEM VALIDAÇÃO",
                "PAULA JULIÃO"
            ],
            "DIAS RECORRENTE": [
                5.8,
                0.0,
                8.14,
                7.29,
                4.5,
                0.0,
                5.53,
                9.13,
                0.0,
                7.44,
                11.86,
                12.2,
                0.83,
                0.75,
                11.3,
                10.0,
                6.38,
                0.0,
                9.28,
                0.0,
                7.59,
                10.77,
                7.05,
                7.76,
                6.62,
                1.23,
                6.68,
                2.48,
                6.66,
                11.83
            ],
            "NAT ACUMULADO SKU": [
                40.89,
                2.09,
                0.0,
                9.88,
                175.18,
                34.95,
                10.13,
                24.81,
                0.0,
                133.18,
                0.0,
                247.16,
                434.32,
                17.1,
                8.55,
                34.13,
                38.66,
                19.07,
                66.55,
                17.23,
                0.0,
                182.6,
                67.4,
                1.02,
                31.15,
                51.79,
                19.57,
                26.64,
                0.0,
                45.85
            ]
        }
    }
}