{
    "SUGESTÃO": 696409,
    "ESCANEADO": 491135,
    "NAT_GERAL": 19247,
    "GRAFICO": {
        "SEPARAÇÃO": {
            "07:30": 3.2,
            "08:30": 2.72,
            "09:30": 0.14,
            "10:30": 2.77,
            "11:30": 3.04,
            "12:30": 2.56,
            "13:30": 4.04,
            "14:30": 3.01,
            "15:30": 2.2,
            "16:40": 2.69,
            "16:50": 2.62,
            "17:00": 3.09,
            "17:10": 1.94,
            "FECHAMENTO": null
        },
        "RESSUPRIMENTO": {
            "07:30": 0.22,
            "08:30": 0.43,
            "09:30": 0.2,
            "10:30": 0.25,
            "11:30": 0.29,
            "12:30": 0.31,
            "13:30": 0.28,
            "14:30": 0.21,
            "15:30": 0.2,
            "16:40": 0.2,
            "16:50": 0.33,
            "17:00": 0.19,
            "17:10": 0.22,
            "FECHAMENTO": null
        },
        "OVER": {
            "07:30": 0.06,
            "08:30": 0.46,
            "09:30": 0.28,
            "10:30": 0.37,
            "11:30": 0.26,
            "12:30": 0.24,
            "13:30": 0.23,
            "14:30": 0.27,
            "15:30": 0.22,
            "16:40": 0.28,
            "16:50": 0.33,
            "17:00": 0.23,
            "17:10": 0.31,
            "FECHAMENTO": null
        },
        "HOLDING": {
            "07:30": 0.06,
            "08:30": 0.14,
            "09:30": 2.4,
            "10:30": 0.15,
            "11:30": 0.13,
            "12:30": 0.14,
            "13:30": 0.14,
            "14:30": 0.17,
            "15:30": 0.18,
            "16:40": 0.22,
            "16:50": 0.19,
            "17:00": 0.2,
            "17:10": 0.21,
            "FECHAMENTO": null
        },
        "DECANTING": {
            "07:30": 0.59,
            "08:30": 0.14,
            "09:30": 0.34,
            "10:30": 0.14,
            "11:30": 0.17,
            "12:30": 0.12,
            "13:30": 0.1,
            "14:30": 0.13,
            "15:30": 0.11,
            "16:40": 0.14,
            "16:50": 0.1,
            "17:00": 0.1,
            "17:10": 0.09,
            "FECHAMENTO": null
        },
        "SUGESTÃO ACIMA DO SALDO": {
            "07:30": 0.0,
            "08:30": 0.09,
            "09:30": 0.32,
            "10:30": 0.07,
            "11:30": 0.07,
            "12:30": 0.07,
            "13:30": 0.06,
            "14:30": 0.07,
            "15:30": 0.05,
            "16:40": 0.08,
            "16:50": 0.12,
            "17:00": 0.12,
            "17:10": 0.15,
            "FECHAMENTO": null
        },
        "VENCIDO": {
            "07:30": 0.0,
            "08:30": 0.05,
            "09:30": 0.16,
            "10:30": 0.06,
            "11:30": 0.07,
            "12:30": 0.06,
            "13:30": 0.06,
            "14:30": 0.04,
            "15:30": 0.06,
            "16:40": 0.05,
            "16:50": 0.06,
            "17:00": 0.04,
            "17:10": 0.05,
            "FECHAMENTO": null
        },
        "SUGESTÃO ACIMA DA CAP.": {
            "07:30": 0.11,
            "08:30": 0.06,
            "09:30": 0.16,
            "10:30": 0.03,
            "11:30": 0.03,
            "12:30": 0.04,
            "13:30": 0.03,
            "14:30": 0.03,
            "15:30": 0.03,
            "16:40": 0.02,
            "16:50": 0.02,
            "17:00": 0.03,
            "17:10": 0.02,
            "FECHAMENTO": null
        },
        "DROP'S": {
            "07:30": 0.1,
            "08:30": 0.03,
            "09:30": 0.12,
            "10:30": 0.02,
            "11:30": 0.04,
            "12:30": 0.04,
            "13:30": 0.04,
            "14:30": 0.03,
            "15:30": 0.04,
            "16:40": 0.09,
            "16:50": 0.12,
            "17:00": 0.08,
            "17:10": 0.11,
            "FECHAMENTO": null
        },
        "GEOGRÁFICO": {
            "07:30": 0.67,
            "08:30": 0.02,
            "09:30": 0.06,
            "10:30": 0.02,
            "11:30": 0.03,
            "12:30": 0.04,
            "13:30": 0.02,
            "14:30": 0.02,
            "15:30": 0.02,
            "16:40": 0.04,
            "16:50": 0.05,
            "17:00": 0.03,
            "17:10": 0.04,
            "FECHAMENTO": null
        },
        "ABASTECIMENTO": {
            "07:30": 0.0,
            "08:30": 0.01,
            "09:30": 0.03,
            "10:30": 0.01,
            "11:30": 0.01,
            "12:30": 0.01,
            "13:30": 0.01,
            "14:30": 0.01,
            "15:30": 0.01,
            "16:40": 0.0,
            "16:50": 0.0,
            "17:00": 0.0,
            "17:10": 0.0,
            "FECHAMENTO": null
        },
        "100% Ñ AT.": {
            "07:30": 0.0,
            "08:30": 0.0,
            "09:30": 0.02,
            "10:30": 0.0,
            "11:30": 0.0,
            "12:30": 0.0,
            "13:30": 0.0,
            "14:30": 0.0,
            "15:30": 0.0,
            "16:40": 0.0,
            "16:50": 0.0,
            "17:00": 0.0,
            "17:10": 0.0,
            "FECHAMENTO": null
        },
        "ENTRADA": {
            "07:30": 0.25,
            "08:30": 0.0,
            "09:30": 0.0,
            "10:30": 0.0,
            "11:30": 0.0,
            "12:30": 0.0,
            "13:30": 0.0,
            "14:30": 0.0,
            "15:30": 0.0,
            "16:40": 0.0,
            "16:50": 0.0,
            "17:00": 0.0,
            "17:10": 0.0,
            "FECHAMENTO": null
        },
        "SUJEIRA": {
            "07:30": 0.0,
            "08:30": 0.0,
            "09:30": 0.0,
            "10:30": 0.39,
            "11:30": 0.42,
            "12:30": 0.29,
            "13:30": 0.39,
            "14:30": 0.46,
            "15:30": 0.31,
            "16:40": 1.81,
            "16:50": 1.38,
            "17:00": 1.67,
            "17:10": 1.16,
            "FECHAMENTO": null
        },
        "SALDO ZERO": {
            "07:30": 0.0,
            "08:30": 0.0,
            "09:30": 0.0,
            "10:30": 0.11,
            "11:30": 0.08,
            "12:30": 0.08,
            "13:30": 0.08,
            "14:30": 0.12,
            "15:30": 0.08,
            "16:40": 0.18,
            "16:50": 0.19,
            "17:00": 0.18,
            "17:10": 0.18,
            "FECHAMENTO": null
        },
        "SALDO DISTRIBUIDO": {
            "07:30": 0.12,
            "08:30": 0.0,
            "09:30": 0.0,
            "10:30": 0.0,
            "11:30": 0.0,
            "12:30": 0.0,
            "13:30": 0.0,
            "14:30": 0.0,
            "15:30": 0.0,
            "16:40": 0.0,
            "16:50": 0.0,
            "17:00": 0.0,
            "17:10": 0.0,
            "FECHAMENTO": null
        },
        "MÁQUINA": {
            "07:30": 0.0,
            "08:30": 0.0,
            "09:30": 0.0,
            "10:30": 0.03,
            "11:30": 0.04,
            "12:30": 0.04,
            "13:30": 0.05,
            "14:30": 0.05,
            "15:30": 0.04,
            "16:40": 0.06,
            "16:50": 0.04,
            "17:00": 0.06,
            "17:10": 0.04,
            "FECHAMENTO": null
        },
        "MISTURADO": {
            "07:30": 0.0,
            "08:30": 0.0,
            "09:30": 0.0,
            "10:30": 0.0,
            "11:30": 0.0,
            "12:30": 0.0,
            "13:30": 0.0,
            "14:30": 0.0,
            "15:30": 0.0,
            "16:40": 0.0,
            "16:50": 0.0,
            "17:00": 0.0,
            "17:10": 0.0,
            "FECHAMENTO": null
        },
        "SEM SALDO": {
            "07:30": 0.0,
            "08:30": 0.0,
            "09:30": 0.0,
            "10:30": 0.0,
            "11:30": 0.0,
            "12:30": 0.0,
            "13:30": 0.0,
            "14:30": 0.0,
            "15:30": 0.0,
            "16:40": 0.0,
            "16:50": 0.0,
            "17:00": 0.0,
            "17:10": 0.0,
            "FECHAMENTO": null
        },
        "MOVIMENTAÇÃO": {
            "07:30": 0.0,
            "08:30": 0.0,
            "09:30": 0.0,
            "10:30": 0.03,
            "11:30": 0.03,
            "12:30": 0.04,
            "13:30": 0.03,
            "14:30": 0.02,
            "15:30": 0.04,
            "16:40": 0.02,
            "16:50": 0.02,
            "17:00": 0.02,
            "17:10": 0.02,
            "FECHAMENTO": null
        },
        "CADASTRO": {
            "07:30": 0.0,
            "08:30": 0.0,
            "09:30": 0.0,
            "10:30": 0.0,
            "11:30": 0.0,
            "12:30": 0.0,
            "13:30": 0.0,
            "14:30": 0.0,
            "15:30": 0.0,
            "16:40": 0.0,
            "16:50": 0.0,
            "17:00": 0.0,
            "17:10": 0.0,
            "FECHAMENTO": null
        },
        "DESVIO DE QUALIDADE": {
            "07:30": 0.0,
            "08:30": 0.0,
            "09:30": 0.0,
            "10:30": 0.0,
            "11:30": 0.0,
            "12:30": 0.0,
            "13:30": 0.0,
            "14:30": 0.0,
            "15:30": 0.0,
            "16:40": 0.0,
            "16:50": 0.0,
            "17:00": 0.0,
            "17:10": 0.0,
            "FECHAMENTO": null
        },
        "SISTEMA": {
            "07:30": 0.0,
            "08:30": 0.0,
            "09:30": 0.0,
            "10:30": 0.0,
            "11:30": 0.0,
            "12:30": 0.0,
            "13:30": 0.0,
            "14:30": 0.0,
            "15:30": 0.0,
            "16:40": 0.0,
            "16:50": 0.0,
            "17:00": 0.0,
            "17:10": 0.0,
            "FECHAMENTO": null
        },
        "RECEBIMENTO": {
            "07:30": 0.0,
            "08:30": 0.0,
            "09:30": 0.0,
            "10:30": 0.0,
            "11:30": 0.0,
            "12:30": 0.0,
            "13:30": 0.0,
            "14:30": 0.0,
            "15:30": 0.0,
            "16:40": 0.0,
            "16:50": 0.0,
            "17:00": 0.0,
            "17:10": 0.0,
            "FECHAMENTO": null
        },
        "NAT": {
            "07:30": 5.24,
            "08:30": 3.47,
            "09:30": 4.32,
            "10:30": 4.27,
            "11:30": 4.53,
            "12:30": 5.71,
            "13:30": 4.07,
            "14:30": 4.91,
            "15:30": 4.17,
            "16:40": 4.91,
            "16:50": 6.96,
            "17:00": 4.06,
            "17:10": 4.95,
            "FECHAMENTO": null
        },
        "INBOUND": {
            "07:30": 1.42,
            "08:30": 0.82,
            "09:30": 1.05,
            "10:30": 0.82,
            "11:30": 0.8,
            "12:30": 0.52,
            "13:30": 0.62,
            "14:30": 0.89,
            "15:30": 0.69,
            "16:40": 0.76,
            "16:50": 0.94,
            "17:00": 0.77,
            "17:10": 0.93,
            "FECHAMENTO": null
        },
        "PRODUÇÃO": {
            "07:30": 2.48,
            "08:30": 2.35,
            "09:30": 1.82,
            "10:30": 3.92,
            "11:30": 3.98,
            "12:30": 4.26,
            "13:30": 3.9,
            "14:30": 3.24,
            "15:30": 4.09,
            "16:40": 3.17,
            "16:50": 4.97,
            "17:00": 3.15,
            "17:10": 4.4,
            "FECHAMENTO": null
        },
        "PCP": {
            "07:30": 0.66,
            "08:30": 0.52,
            "09:30": 0.43,
            "10:30": 0.42,
            "11:30": 0.36,
            "12:30": 0.49,
            "13:30": 0.5,
            "14:30": 0.33,
            "15:30": 0.31,
            "16:40": 0.42,
            "16:50": 0.44,
            "17:00": 0.63,
            "17:10": 0.58,
            "FECHAMENTO": null
        },
        "OUTROS": {
            "07:30": 0.0,
            "08:30": 0.0,
            "09:30": 0.0,
            "10:30": 0.0,
            "11:30": 0.0,
            "12:30": 0.0,
            "13:30": 0.0,
            "14:30": 0.0,
            "15:30": 0.0,
            "16:40": 0.0,
            "16:50": 0.0,
            "17:00": 0.0,
            "17:10": 0.0,
            "FECHAMENTO": null
        },
        "META": {
            "SEPARAÇÃO": 2.15,
            "ENTRADA": 0.24,
            "SUJEIRA": 1,
            "DECANTING": 0.33,
            "SALDO ZERO": 0.47,
            "RESSUPRIMENTO": 0.69,
            "HOLDING": 0.28,
            "DROP'S": 0.34,
            "OVER": 0.45,
            "MÁQUINA": 0,
            "ABASTECIMENTO": 0.04,
            "SALDO DISTRIBUIDO": 0,
            "MISTURADO": 0,
            "INVENTÁRIO": 0,
            "SUGESTÃO ACIMA DA CAP.": 0.16,
            "SUGESTÃO ACIMA DO SALDO": 0,
            "100% Ñ AT.": 0,
            "MOVIMENTAÇÃO": 0,
            "CADASTRO": 0,
            "SEM SALDO": 0,
            "DESVIO DE QUALIDADE": 0,
            "SISTEMA": 0,
            "VENCIDO": 0,
            "RECEBIMENTO": 0,
            "PRODUÇÃO": 2.64,
            "INBOUND": 2.13,
            "PCP": 0,
            "OUTROS": 0
        }
    },
    "TOP3": {
        "SEPARAÇÃO": {
            "SKU": [
                81196.85,
                66349.57,
                43741.84
            ],
            "DESCRIÇÃO": [
                "FIASP FLEXTOU 100U 3ML (var)",
                "CIMELIDE 12'S",
                "VALDA FRIE CANELA 25G"
            ],
            "SUGESTÃO": [
                685.0,
                364.6,
                212.37
            ],
            "FATURADO": [
                523.46,
                164.27,
                0.0
            ],
            "NAT": [
                127.92,
                64.54,
                98.68
            ]
        },
        "SUJEIRA": {
            "SKU": [
                43472.63,
                288603.44,
                66951.41
            ],
            "DESCRIÇÃO": [
                "PREDNISOL 20MG EMG 10S (var)",
                "VALSARTA 160MG CIG 30S",
                "REACH FIO D MENT 50"
            ],
            "SUGESTÃO": [
                599.86,
                129.26,
                152.98
            ],
            "FATURADO": [
                418.44,
                0.0,
                119.02
            ],
            "NAT": [
                171.13,
                112.13,
                98.05
            ]
        },
        "DECANTING": {
            "SKU": [
                562226.79,
                175540.28,
                1186562.96
            ],
            "DESCRIÇÃO": [
                "SENSOD CR REPAIR 2X100",
                "FOREV LISS MASC B.VERN",
                "NEEDS POL CAB E UNH 60"
            ],
            "SUGESTÃO": [
                98.01,
                91.43,
                72.04
            ],
            "FATURADO": [
                15.37,
                0.0,
                35.13
            ],
            "NAT": [
                51.08,
                42.09,
                28.24
            ]
        },
        "RESSUPRIMENTO": {
            "SKU": [
                34428.74,
                60852.54,
                12972.11
            ],
            "DESCRIÇÃO": [
                "*SERTRALI 50 CIG 30-C1",
                "COLG CR DENT ORTHOG 90 (var)",
                "ANASTROZOL 1EUG 30'S"
            ],
            "SUGESTÃO": [
                416.74,
                123.57,
                60.89
            ],
            "FATURADO": [
                213.53,
                37.67,
                0.0
            ],
            "NAT": [
                65.01,
                82.49,
                58.66
            ]
        },
        "MÁQUINA": {
            "SKU": [
                36228.56,
                811821.3,
                44927.9
            ],
            "DESCRIÇÃO": [
                "METOPROLOL 50MG NQG 30",
                "MIOSAN CAF 10/60MG 15S",
                "ELSEVEÂ ACÂ GLYCOL 200ML"
            ],
            "SUGESTÃO": [
                148.99,
                75.3,
                77.14
            ],
            "FATURADO": [
                57.71,
                0.0,
                55.12
            ],
            "NAT": [
                49.45,
                31.7,
                43.87
            ]
        },
        "SALDO ZERO": {
            "SKU": [
                69293.98,
                733043.96,
                864633.76
            ],
            "DESCRIÇÃO": [
                "TREZETE 10+10MG 30'S (var)",
                "PREDSIM 20MG 20'S",
                "BWELL VIT C LB 500MG30"
            ],
            "SUGESTÃO": [
                191.32,
                85.94,
                101.21
            ],
            "FATURADO": [
                54.01,
                21.03,
                46.32
            ],
            "NAT": [
                94.88,
                67.07,
                38.87
            ]
        },
        "SUGESTÃO ACIMA DO SALDO": {
            "SKU": [
                62714.42,
                896763.61,
                102393.71
            ],
            "DESCRIÇÃO": [
                "OZEMPIC 1MG 4AGULHAS (var)",
                "BIORE UV F50 A/RICH 70",
                "NUVARING ANEL VAG 1 UN"
            ],
            "SUGESTÃO": [
                419.94,
                157.48,
                166.95
            ],
            "FATURADO": [
                133.25,
                81.92,
                105.64
            ],
            "NAT": [
                83.96,
                49.85,
                52.88
            ]
        },
        "ABASTECIMENTO": {
            "SKU": [
                58481.68
            ],
            "DESCRIÇÃO": [
                "ATORVAST 40MG EMG 30'S"
            ],
            "SUGESTÃO": [
                689.9
            ],
            "FATURADO": [
                616.73
            ],
            "NAT": [
                1.17
            ]
        },
        "OVER": {
            "SKU": [
                72215.18,
                24005.38,
                33462.76
            ],
            "DESCRIÇÃO": [
                "MYLANTA PLUS MOR 240ML",
                "KELTRINA PL 5% LC 60ML",
                "NEOSALDINA 15ML GTA"
            ],
            "SUGESTÃO": [
                190.93,
                159.02,
                60.5
            ],
            "FATURADO": [
                13.08,
                107.68,
                17.35
            ],
            "NAT": [
                74.35,
                59.37,
                46.45
            ]
        },
        "DROP'S": {
            "SKU": [
                7754.87,
                12845.59,
                149961.8
            ],
            "DESCRIÇÃO": [
                "DAONIL 30'S",
                "LISTERINE A TART 250ML",
                "NEEDS MASC DESC INF 5U"
            ],
            "SUGESTÃO": [
                147.87,
                69.31,
                67.83
            ],
            "FATURADO": [
                40.48,
                26.27,
                0.0
            ],
            "NAT": [
                69.58,
                71.15,
                31.56
            ]
        },
        "HOLDING": {
            "SKU": [
                80006.9,
                143420.08,
                30903.22
            ],
            "DESCRIÇÃO": [
                "RISQUE CARE COB BR 8ML",
                "STANGLIT 30 MG 60'S",
                "BITUFO ESC CLASS ORTO"
            ],
            "SUGESTÃO": [
                135.52,
                97.83,
                63.83
            ],
            "FATURADO": [
                0.0,
                63.97,
                7.64
            ],
            "NAT": [
                120.48,
                64.27,
                35.28
            ]
        },
        "SUGESTÃO ACIMA DA CAP.": {
            "SKU": [
                366013.6,
                645366.12
            ],
            "DESCRIÇÃO": [
                "NEEDS ENX ZERO MEN 500",
                "EPISOL ACQUA F60 60ML (var)"
            ],
            "SUGESTÃO": [
                181.45,
                137.88
            ],
            "FATURADO": [
                0.0,
                73.47
            ],
            "NAT": [
                103.18,
                0.78
            ]
        },
        "GEOGRÁFICO": {
            "SKU": [
                62187.18,
                1091562.51,
                458145.6
            ],
            "DESCRIÇÃO": [
                "LRP EFF GEL ALT TOL 60",
                "M.BONI ESC OVAL COCONU",
                "NEUTR NORW HD C/FR 400"
            ],
            "SUGESTÃO": [
                47.94,
                62.33,
                32.75
            ],
            "FATURADO": [
                0.0,
                0.0,
                10.82
            ],
            "NAT": [
                76.64,
                44.86,
                13.77
            ]
        },
        "MOVIMENTAÇÃO": {
            "SKU": [
                152931.15,
                134908.71
            ],
            "DESCRIÇÃO": [
                "APTANUTRI PROF 3 800G",
                "NANLAC SUPREME 1+ 800G"
            ],
            "SUGESTÃO": [
                271.89,
                185.59
            ],
            "FATURADO": [
                117.93,
                96.05
            ],
            "NAT": [
                35.43,
                30.58
            ]
        },
        "SALDO DISTRIBUIDO": {
            "SKU": [
                419462.37
            ],
            "DESCRIÇÃO": [
                "PANTOGAR SILICIO 30UN (var)"
            ],
            "SUGESTÃO": [
                13.35
            ],
            "FATURADO": [
                7.35
            ],
            "NAT": [
                3.64
            ]
        },
        "VENCIDO": {
            "SKU": [
                9668.36
            ],
            "DESCRIÇÃO": [
                "NEOLEFRIN 20'S (var)"
            ],
            "SUGESTÃO": [
                263.83
            ],
            "FATURADO": [
                0.0
            ],
            "NAT": [
                205.64
            ]
        },
        "PRODUÇÃO": {
            "SKU": [
                9745.3,
                99171.88,
                55114.69
            ],
            "DESCRIÇÃO": [
                "NEOLEFRIN 20'S (var)",
                "FIASP FLEXTOU 100U 3ML",
                "VALDA FRIE CANELA 25G"
            ],
            "SUGESTÃO": [
                271.29,
                326.02,
                193.63
            ],
            "FATURADO": [
                0.0,
                267.61,
                0.0
            ],
            "NAT": [
                75.63,
                264.3,
                83.33
            ]
        },
        "INBOUND": {
            "SKU": [
                91130.82,
                305528.82,
                54628.96
            ],
            "DESCRIÇÃO": [
                "TREZETE 10+10MG 30'S",
                "VALSARTA 160MG CIG 30S",
                "RISQUE CARE COB BR 8ML"
            ],
            "SUGESTÃO": [
                148.93,
                89.53,
                174.67
            ],
            "FATURADO": [
                31.75,
                0.0,
                0.0
            ],
            "NAT": [
                80.53,
                103.65,
                98.51
            ]
        },
        "PCP": {
            "SKU": [
                37812.13,
                15302.24,
                50597.44
            ],
            "DESCRIÇÃO": [
                "PREDNISOL 20MG EMG 10S",
                "MYLANTA PLUS MOR 240ML",
                "CIMELIDE 12'S (var)"
            ],
            "SUGESTÃO": [
                474.23,
                178.95,
                1025.03
            ],
            "FATURADO": [
                356.4,
                87.02,
                560.5
            ],
            "NAT": [
                168.9,
                110.44,
                74.9
            ]
        },
        "OUTROS": {
            "SKU": [
                37629.49,
                535189.25,
                62722.93
            ],
            "DESCRIÇÃO": [
                "OZEMPIC 1MG 4AGULHAS",
                "BIORE UV F50 A/RICH 70",
                "NUVARING ANEL VAG 1 UN"
            ],
            "SUGESTÃO": [
                271.08,
                195.34,
                231.48
            ],
            "FATURADO": [
                161.34,
                74.83,
                134.65
            ],
            "NAT": [
                120.31,
                42.69,
                54.67
            ]
        },
        "NAT": {
            "SKU": [
                27420.48,
                68921.8,
                9983.12
            ],
            "DESCRIÇÃO": [
                "NEOLEFRIN 20'S (var)",
                "TREZETE 10+10MG 30'S",
                "PREDNISOL 20MG EMG 10S"
            ],
            "SUGESTÃO": [
                550.95,
                363.19,
                125.81
            ],
            "FATURADO": [
                0.0,
                321.35,
                38.71
            ],
            "NAT": [
                318.98,
                156.16,
                101.43
            ]
        }
    },
    "OFENSORES": {
        "1": "Unidades de SEPARAÇÃO: 11019",
        "2": "Unidades de RESSUPRIMENTO: 1160",
        "3": "Unidades de OVER: 1254",
        "PREVISÃO": "EM BREVE"
    },
    "NAT_POR_SETOR": {
        "07:30": {
            "M": 0.0,
            "V": 0.63,
            "Y": 0.0,
            "H": 1.29,
            "W": 0.27,
            "N": 0.09,
            "G": 0.0,
            "I": 0.0,
            "A": 0.04,
            "J": 0.78,
            "X": 0.03,
            "S": 0.0,
            "F": 0.0,
            "D": 0.23,
            "K": 0.1,
            "Z": 0.07,
            "L": 0.06,
            "O": 0.0,
            "C": 0.0,
            "T": 0.0,
            "U": 0.0,
            "B": 0.0,
            "R": 0.0
        },
        "08:30": {
            "M": 0.81,
            "V": 0.95,
            "Y": 1.08,
            "H": 0.42,
            "W": 0.1,
            "N": 0.03,
            "G": 0.0,
            "I": 0.0,
            "A": 0.35,
            "J": 0.0,
            "X": 0.32,
            "S": 0.0,
            "F": 0.0,
            "D": 0.17,
            "K": 0.11,
            "Z": 0.1,
            "L": 0.04,
            "O": 0.0,
            "C": 0.0,
            "T": 0.0,
            "U": 0.0,
            "B": 0.0,
            "R": 0.0
        },
        "09:30": {
            "M": 0.79,
            "V": 1.25,
            "Y": 0.76,
            "H": 0.66,
            "W": 0.05,
            "N": 0.02,
            "G": 0.01,
            "I": 0.0,
            "A": 0.21,
            "J": 0.16,
            "X": 0.04,
            "S": 0.0,
            "F": 0.0,
            "D": 0.23,
            "K": 0.08,
            "Z": 0.13,
            "L": 0.06,
            "O": 0.0,
            "C": 0.0,
            "T": 0.01,
            "U": 0.0,
            "B": 0.0,
            "R": 0.0
        },
        "10:30": {
            "M": 1.09,
            "V": 0.97,
            "Y": 1.06,
            "H": 0.65,
            "W": 0.11,
            "N": 0.02,
            "G": 0.0,
            "I": 0.0,
            "A": 0.35,
            "J": 0.0,
            "X": 0.39,
            "S": 0.0,
            "F": 0.0,
            "D": 0.14,
            "K": 0.07,
            "Z": 0.08,
            "L": 0.04,
            "O": 0.0,
            "C": 0.0,
            "T": 0.0,
            "U": 0.0,
            "B": 0.0,
            "R": 0.0
        },
        "11:30": {
            "M": 1.2,
            "V": 1.32,
            "Y": 1.05,
            "H": 0.5,
            "W": 0.11,
            "N": 0.03,
            "G": 0.0,
            "I": 0.0,
            "A": 0.27,
            "J": 0.0,
            "X": 0.26,
            "S": 0.0,
            "F": 0.0,
            "D": 0.16,
            "K": 0.1,
            "Z": 0.11,
            "L": 0.03,
            "O": 0.0,
            "C": 0.0,
            "T": 0.0,
            "U": 0.0,
            "B": 0.0,
            "R": 0.0
        },
        "12:30": {
            "M": 0.81,
            "V": 1.07,
            "Y": 0.84,
            "H": 0.54,
            "W": 0.1,
            "N": 0.02,
            "G": 0.0,
            "I": 0.0,
            "A": 0.4,
            "J": 0.0,
            "X": 0.34,
            "S": 0.0,
            "F": 0.0,
            "D": 0.26,
            "K": 0.08,
            "Z": 0.1,
            "L": 0.04,
            "O": 0.0,
            "C": 0.0,
            "T": 0.0,
            "U": 0.0,
            "B": 0.0,
            "R": 0.0
        },
        "13:30": {
            "M": 1.0,
            "V": 0.91,
            "Y": 1.1,
            "H": 0.57,
            "W": 0.11,
            "N": 0.02,
            "G": 0.0,
            "I": 0.0,
            "A": 0.23,
            "J": 0.0,
            "X": 0.22,
            "S": 0.0,
            "F": 0.0,
            "D": 0.25,
            "K": 0.07,
            "Z": 0.11,
            "L": 0.03,
            "O": 0.0,
            "C": 0.0,
            "T": 0.0,
            "U": 0.0,
            "B": 0.0,
            "R": 0.0
        },
        "14:30": {
            "M": 1.17,
            "V": 1.32,
            "Y": 1.11,
            "H": 0.62,
            "W": 0.09,
            "N": 0.02,
            "G": 0.0,
            "I": 0.0,
            "A": 0.35,
            "J": 0.0,
            "X": 0.34,
            "S": 0.0,
            "F": 0.0,
            "D": 0.19,
            "K": 0.07,
            "Z": 0.08,
            "L": 0.04,
            "O": 0.0,
            "C": 0.0,
            "T": 0.0,
            "U": 0.0,
            "B": 0.0,
            "R": 0.0
        },
        "15:30": {
            "M": 1.15,
            "V": 0.95,
            "Y": 0.74,
            "H": 0.55,
            "W": 0.11,
            "N": 0.02,
            "G": 0.0,
            "I": 0.0,
            "A": 0.26,
            "J": 0.0,
            "X": 0.23,
            "S": 0.0,
            "F": 0.0,
            "D": 0.26,
            "K": 0.06,
            "Z": 0.1,
            "L": 0.03,
            "O": 0.0,
            "C": 0.0,
            "T": 0.0,
            "U": 0.0,
            "B": 0.0,
            "R": 0.0
        },
        "16:40": {
            "M": 0.89,
            "V": 0.89,
            "Y": 1.09,
            "H": 0.54,
            "W": 0.08,
            "N": 0.04,
            "G": 0.11,
            "I": 0.0,
            "A": 0.22,
            "J": 0.03,
            "X": 0.21,
            "S": 0.0,
            "F": 0.0,
            "D": 0.13,
            "K": 0.08,
            "Z": 0.09,
            "L": 0.02,
            "O": 0.0,
            "C": 0.0,
            "T": 0.0,
            "U": 0.0,
            "B": 0.0,
            "R": 0.0
        },
        "16:50": {
            "M": 0.97,
            "V": 1.26,
            "Y": 1.18,
            "H": 0.61,
            "W": 0.07,
            "N": 0.05,
            "G": 0.17,
            "I": 0.0,
            "A": 0.23,
            "J": 0.02,
            "X": 0.19,
            "S": 0.0,
            "F": 0.0,
            "D": 0.19,
            "K": 0.07,
            "Z": 0.13,
            "L": 0.02,
            "O": 0.0,
            "C": 0.0,
            "T": 0.0,
            "U": 0.0,
            "B": 0.0,
            "R": 0.0
        },
        "17:00": {
            "M": 1.16,
            "V": 1.18,
            "Y": 1.3,
            "H": 0.93,
            "W": 0.04,
            "N": 0.05,
            "G": 0.17,
            "I": 0.0,
            "A": 0.24,
            "J": 0.02,
            "X": 0.16,
            "S": 0.0,
            "F": 0.0,
            "D": 0.21,
            "K": 0.08,
            "Z": 0.09,
            "L": 0.01,
            "O": 0.0,
            "C": 0.0,
            "T": 0.0,
            "U": 0.0,
            "B": 0.0,
            "R": 0.0
        },
        "17:10": {
            "M": 1.54,
            "V": 0.86,
            "Y": 1.34,
            "H": 0.9,
            "W": 0.04,
            "N": 0.05,
            "G": 0.28,
            "I": 0.0,
            "A": 0.22,
            "J": 0.03,
            "X": 0.15,
            "S": 0.0,
            "F": 0.0,
            "D": 0.18,
            "K": 0.08,
            "Z": 0.08,
            "L": 0.02,
            "O": 0.0,
            "C": 0.0,
            "T": 0.0,
            "U": 0.0,
            "B": 0.0,
            "R": 0.0
        }
    },
    "OFENSORES_RESUMO": {
        "MAIORES": {
            "SKU": [
                14294.13,
                38564.41,
                59714.06,
                97213.91,
                22191.52,
                61496.67,
                238366.93,
                61077.65,
                38445.62,
                595394.55,
                47744.74,
                5655.09,
                65624.59,
                57539.47,
                788253.41,
                108260.24,
                740.1,
                12474.53,
                38762.47,
                32948.48,
                24976.53,
                61156.21,
                71009.52,
                24576.52,
                20218.84,
                33638.27,
                199161.61,
                18797.79,
                1141610.6,
                11797.08
            ],
            "DESCRIÇÃO": [
                "LANTUS SOLOSTAR 3ML",
                "DOVE SAB LQ SENS 250M",
                "PANTOPRAZOL 40MEG 14'S",
                "NEEDS ESP IMP BG 1,2X3",
                "XULTOPHY 3ML 1 APLIC (var)",
                "OZEMPIC 1MG 4AGULHAS",
                "TREZETE 10+10MG 30'S",
                "OSCILLOC 200K C/6",
                "VITERGAN ZINCO PL 30'S",
                "RISQUE GEL CREM LOOK F",
                "NEOLEFRIN 20'S",
                "PREDNISOL 20MG EMG 10S",
                "MYLANTA PLUS MOR 240ML",
                "*SERTRALI 50 CIG 30-C1",
                "RISQUE CARE COB BR 8ML",
                "LISTERINE A TART 250ML",
                "DAONIL 30'S",
                "CIMELIDE 12'S",
                "NEEDS ENX ZERO MEN 500 (var)",
                "VALDA FRIE CANELA 25G",
                "MIOSAN 5MG 30'S",
                "VALSARTA 160MG CIG 30S (var)",
                "*FLUOXET 20 TEG 30S-C1 (var)",
                "COLG CR DENT ORTHOG 90",
                "*QUETIAP 25 TEG 30S-C1",
                "FIASP FLEXTOU 100U 3ML",
                "LRP EFF GEL ALT TOL 60",
                "ANASTROZOL 1EUG 30'S (var)",
                "REACH FIO D MENT 50",
                "NEOSALDINA 15ML GTA"
            ],
            "SETOR": [
                "D",
                "V",
                "M",
                "G",
                "M",
                "M (var)",
                "V",
                "H",
                "G",
                "Y",
                "W",
                "M",
                "V",
                "H",
                "H",
                "M (var)",
                "V",
                "A",
                "A",
                "G",
                "A",
                "Y",
                "H",
                "V",
                "V",
                "G",
                "M",
                "M (var)",
                "H (var)",
                "Y"
            ],
            "ENDEREÇO": [
                "5-D-07-013-03",
                "7-V-06-007-03",
                "7-M-26-007-04",
                "6-G-01-006-03",
                "7-M-04-007-04",
                "7-M-17-007-03",
                "7-V-07-026-03",
                "7-H-03-016-05",
                "6-G-01-001-03",
                "7-Y-08-007-03",
                "6-W-09-005-03",
                "7-M-13-016-03",
                "7-V-19-019-05",
                "7-H-13-001-04",
                "7-H-17-019-06",
                "7-M-18-022-03",
                "7-V-01-011-01",
                "6-A-06-011-03",
                "6-A-11-031-04",
                "6-G-01-002-04",
                "6-A-13-011-03",
                "7-Y-17-002-04",
                "7-H-21-017-05",
                "7-V-32-021-03",
                "7-V-09-015-02",
                "6-G-01-005-02 (var)",
                "7-M-14-019-06",
                "7-M-11-017-04",
                "7-H-03-018-01",
                "7-Y-18-017-02"
            ],
            "SUGESTÃO TOTAL": [
                260.75,
                585.45,
                152.19,
                450.17,
                260.34,
                774.89,
                136.09,
                137.07,
                368.53,
                138.8,
                141.66,
                162.1,
                84.42,
                165.75,
                77.33,
                166.06,
                154.84,
                110.65,
                456.39,
                203.39,
                344.1,
                208.28,
                72.6,
                90.48,
                59.63,
                219.41,
                92.06,
                96.43,
                58.37,
                111.91
            ],
            "UNID. FATURADAS": [
                0.0,
                363.12,
                42.34,
                162.69,
                109.78,
                777.33,
                0.0,
                0.0,
                212.25,
                0.0,
                0.0,
                55.37,
                0.0,
                114.02,
                0.0,
                19.25,
                37.36,
                0.0,
                256.25,
                157.52,
                292.12,
                46.05,
                0.0,
                0.0,
                0.0,
                87.52,
                20.28,
                3.09,
                0.0,
                0.0
            ],
            "UNID. NAT": [
                220.12,
                166.28,
                110.22,
                81.29,
                98.2,
                80.25,
                122.33,
                86.3,
                103.85,
                70.94,
                72.46,
                86.33,
                68.4,
                83.57,
                91.55,
                89.07,
                75.13,
                60.41,
                89.93,
                54.81,
                54.07,
                71.27,
                62.22,
                52.31,
                77.64,
                81.98,
                52.91,
                81.92,
                67.95,
                63.88
            ],
            "SALDO INICIAL": [
                832.64,
                472.6,
                131.33,
                6729.63,
                46.15,
                447.4,
                71.4,
                119.12,
                13.61,
                0.0,
                505.02,
                88.48,
                117.29,
                817.46,
                57.12,
                146.27,
                434.0,
                1422.29,
                103.83,
                8665.25,
                351.22,
                25.16,
                1.8,
                389.08,
                58.05,
                5621.69,
                196.6,
                18.36,
                174.62,
                11.66
            ],
            "SALDO CASE": [
                0.0,
                2749.92,
                0.0,
                0.0,
                413.63,
                435.43,
                14.92,
                0.0,
                0.0,
                0.0,
                0.0,
                269.32,
                17.09,
                407.73,
                401.0,
                160.61,
                54.79,
                0.0,
                0.0,
                0.0,
                0.0,
                57.85,
                0.0,
                0.0,
                0.0,
                0.0,
                451.92,
                242.68,
                0.0,
                132.59
            ],
            "STATUS NÃO ATENDIMENTO": [
                "RESSUPRIMENTO",
                "SEPARAÇÃO",
                "SEPARAÇÃO",
                "SUGESTÃO ACIMA DA CAP. (var)",
                "HOLDING",
                "OVER",
                "SEPARAÇÃO",
                "OVER",
                "SEPARAÇÃO",
                "GEOGRÁFICO",
                "SEPARAÇÃO",
                "SUGESTÃO ACIMA DO SALDO",
                "OVER",
                "RESSUPRIMENTO",
                "HOLDING",
                "SEPARAÇÃO",
                "SEPARAÇÃO",
                "OVER",
                "SEPARAÇÃO",
                "OVER",
                "SEPARAÇÃO",
                "SEPARAÇÃO",
                "SEPARAÇÃO",
                "SEPARAÇÃO",
                "OVER (var)",
                "RESSUPRIMENTO",
                "RESSUPRIMENTO",
                "RESSUPRIMENTO",
                "OVER",
                "SEPARAÇÃO"
            ],
            "STATUS VALIDADO": [
                "VENCIDO",
                "SUJEIRA",
                "SALDO ZERO",
                null,
                null,
                "SEPARAÇÃO",
                "SUJEIRA",
                null,
                null,
                null,
                null,
                "DROP'S",
                null,
                "SUJEIRA",
                "SUJEIRA",
                "OVER",
                "SUJEIRA",
                "SUJEIRA",
                null,
                null,
                "SUJEIRA",
                null,
                null,
                "SUJEIRA (var)",
                null,
                null,
                "SUJEIRA (var)",
                "SUJEIRA",
                "SUJEIRA",
                "DROP'S"
            ],
            "SALDO ATIVO": [
                186.18,
                0.0,
                0.0,
                6051.11,
                9.15,
                0.0,
                63.45,
                117.07,
                2962.18,
                0.0,
                612.28,
                161.26,
                108.46,
                83.87,
                93.04,
                14.4,
                36.09,
                1447.99,
                81.94,
                8905.03,
                184.45,
                264.95,
                2.22,
                131.05,
                0.0,
                3223.01,
                178.77,
                24.37,
                205.12,
                1.02
            ],
            "QUEM VALIDOU": [
                "Luciana",
                "PAULA",
                "ESCANEAMENTO (var)",
                "SEM VALIDAÇÃO",
                "SEM VALIDAÇÃO",
                "PAULA",
                "João (var)",
                "SEM VALIDAÇÃO",
                "SEM VALIDAÇÃO",
                "SEM VALIDAÇÃO",
                "SEM VALIDAÇÃO",
                "Júlio (var)",
                "SEM VALIDAÇÃO",
                "DEBORA",
                "Evandro",
                "Luiz",
                "CAIQUE",
                "TAINA",
                "SEM VALIDAÇÃO",
                "SEM VALIDAÇÃO",
                "TAINA",
                "SEM VALIDAÇÃO",
                "SEM VALIDAÇÃO",
                "CAIQUE",
                "SEM VALIDAÇÃO",
                "SEM VALIDAÇÃO",
                "dennis",
                "Victoria",
                "GABRIEL",
                "PAULA"
            ],
            "DIAS RECORRENTE": [
                9.34,
                10.91,
                10.44,
                1.15,
                4.11,
                5.7,
                3.79,
                6.87,
                0.0,
                5.21,
                0.0,
                9.99,
                6.34,
                11.44,
                7.38,
                10.23,
                8.25,
                9.04,
                1.63,
                0.0,
                0.0,
                8.02,
                7.11,
                7.91,
                1.16,
                0.0,
                9.7,
                0.0,
                0.88,
                5.07
            ],
            "NAT ACUMULADO SKU": [
                86.35,
                1.45,
                11.65,
                10.29,
                422.72,
                25.15,
                95.08,
                0.0,
                0.0,
                15.62,
                126.46,
                277.65,
                7.98,
                10.27,
                43.27,
                0.0,
                241.44,
                0.0,
                13.71,
                0.93,
                417.76,
                18.97,
                27.29,
                34.45,
                9.5,
                59.13,
                12.78,
                0.0,
                8.73,
                0.0
            ]
        },
        "RESSUPRIMENTO": {
            "SKU": [
                97170.23,
                24747.33,
                17229.32,
                56427.37,
                14131.62,
                50115.59,
                39858.27,
                1012072.69,
                651067.36,
                131538.64,
                22.81,
                7295.76,
                98708.39,
                856179.93,
                53612.66,
                52902.21,
                108698.86,
                31798.2,
                18078.3,
                20183.59,
                1419959.41,
                16014.46,
                149078.03,
                994318.4,
                282943.02,
                297818.75,
                103405.7,
                4393.4,
                575856.66,
                104122.5
            ],
            "DESCRIÇÃO": [
                "GRANADO SB BEB CAMOM90",
                "*TRILEPTAL 300MG 60-C1",
                "LEVANLOD 5MG BLG 30S",
                "ACEBROFIL 50MG EMG 120",
                "APTANUTRI PROF 3 800G",
                "DOVE SAB BRANC LMPM C6",
                "NEEDS POL CAB E UNH 60",
                "LUVIS GOLD 60 'S",
                "*ARCOXIA 90MG 5'S-C1",
                "AFTLIV SOL BUCAL 25ML",
                "REVITALIFT ANT OL 49G",
                "IMEDIA TINT 5 47G",
                "HUGG LENC RN 48UN",
                "CLAVULIN 500+125MG 21S (var)",
                "*QUETIAP 25 TEG 30S-C1",
                "NEEDS AG INSULINA 4MM",
                "CIMEGRIPE 20'S",
                "JONTEX PELE C/PELE 12 ",
                "FEMINIS 30'S",
                "SENSIBIO H2O MIC 100ML",
                "INTIM PROT S/P L80P60",
                "NANLAC SUPREME 1+ 800G",
                "COLG CREME XTREME L3P2",
                "COLG CR DENT ORTHOG 90",
                "BETAM+GENT EMS CR 30G",
                "SENSOD CR REPAIR 2X100",
                "ANASTROZOL 1EUG 30'S",
                "J&J BABY OLEO AMEN 200",
                "*SERTRALI 50 CIG 30-C1",
                "TREZETE 10+10MG 30'S"
            ],
            "SETOR": [
                "M",
                "A",
                "A",
                "Y",
                "V",
                "D",
                "Y (var)",
                "Y",
                "H",
                "W (var)",
                "A",
                "N (var)",
                "M",
                "M",
                "Y",
                "Y",
                "W",
                "Y",
                "X",
                "H",
                "V",
                "Z",
                "H",
                "A",
                "M",
                "Y",
                "V",
                "H",
                "M",
                "X (var)"
            ],
            "ENDEREÇO": [
                "5-D-05-006-04",
                "7-Y-06-021-02",
                "6-W-07-011-01",
                "7-V-09-023-04",
                "7-Y-27-003-02",
                "7-V-09-015-02",
                "6-N-07-008-02",
                "6-A-13-011-03",
                "6-A-05-026-03",
                "7-M-21-011-02",
                "7-Y-17-002-04",
                "5-Z-14-005-01",
                "6-A-11-031-04",
                "7-Y-04-012-05",
                "7-Y-20-015-06",
                "7-V-12-016-03",
                "6-X-03-014-05",
                "7-M-13-021-06",
                "7-H-22-001-03",
                "7-H-24-014-04",
                "7-M-26-007-04",
                "7-H-30-026-04",
                "6-W-04-015-01",
                "7-M-09-017-03",
                "7-H-22-011-03 (var)",
                "7-M-27-020-02",
                "7-Y-02-019-04",
                "7-Y-19-002-04",
                "6-A-09-013-06",
                "6-X-02-007-04"
            ],
            "SUGESTÃO TOTAL": [
                220.71,
                538.62,
                382.61,
                216.6,
                58.15,
                3135.51,
                103.67,
                146.58,
                66.94,
                172.86,
                122.17,
                358.02,
                47.02,
                65.36,
                73.37,
                158.08,
                161.3,
                121.72,
                207.28,
                29.02,
                57.8,
                1227.83,
                31.08,
                22.11,
                56.62,
                38.0,
                34.49,
                23.99,
                70.39,
                34.26
            ],
            "UNID. FATURADAS": [
                45.96,
                198.41,
                132.07,
                0.0,
                15.38,
                74.21,
                50.84,
                0.0,
                13.09,
                46.27,
                0.0,
                0.0,
                11.7,
                0.0,
                5.42,
                25.95,
                306.12,
                743.59,
                2183.27,
                18.71,
                0.0,
                288.82,
                66.33,
                0.0,
                95.69,
                128.51,
                15.2,
                8.59,
                56.55,
                51.28
            ],
            "UNID. NAT": [
                137.61,
                53.15,
                90.87,
                69.12,
                66.81,
                69.58,
                58.52,
                53.6,
                43.31,
                53.91,
                44.41,
                34.59,
                38.04,
                26.39,
                41.9,
                43.7,
                43.79,
                41.3,
                41.09,
                35.77,
                28.07,
                29.03,
                21.32,
                19.28,
                27.76,
                20.65,
                18.51,
                18.09,
                25.27,
                18.22
            ],
            "SALDO INICIAL": [
                150.57,
                91.51,
                306.45,
                25.82,
                55.72,
                2757.88,
                54.57,
                22.06,
                61.56,
                84.76,
                30.42,
                188.62,
                40.58,
                60.21,
                18.31,
                53.63,
                114.16,
                62.58,
                68.33,
                23.95,
                26.53,
                169.65,
                5.86,
                11.99,
                20.07,
                12.93,
                0.0,
                3.52,
                35.0,
                45.12
            ],
            "SALDO CASE": [
                0.0,
                0.0,
                0.0,
                53.77,
                0.0,
                0.0,
                0.0,
                0.0,
                0.0,
                0.0,
                0.0,
                0.0,
                0.0,
                26.43,
                12.21,
                0.0,
                0.0,
                59.4,
                0.0,
                0.0,
                0.0,
                0.0,
                0.0,
                0.0,
                19.33,
                0.0,
                0.0,
                3.52,
                0.0,
                0.0
            ],
            "STATUS NÃO ATENDIMENTO": [
                "RESSUPRIMENTO",
                "RESSUPRIMENTO",
                "RESSUPRIMENTO",
                "RESSUPRIMENTO (var)",
                "RESSUPRIMENTO",
                "RESSUPRIMENTO",
                "RESSUPRIMENTO",
                "RESSUPRIMENTO",
                "RESSUPRIMENTO",
                "RESSUPRIMENTO",
                "RESSUPRIMENTO",
                "RESSUPRIMENTO (var)",
                "RESSUPRIMENTO",
                "RESSUPRIMENTO",
                "RESSUPRIMENTO",
                "RESSUPRIMENTO",
                "RESSUPRIMENTO (var)",
                "RESSUPRIMENTO (var)",
                "RESSUPRIMENTO",
                "RESSUPRIMENTO (var)",
                "RESSUPRIMENTO",
                "RESSUPRIMENTO",
                "RESSUPRIMENTO",
                "RESSUPRIMENTO (var)",
                "RESSUPRIMENTO",
                "RESSUPRIMENTO",
                "RESSUPRIMENTO",
                "RESSUPRIMENTO",
                "RESSUPRIMENTO",
                "RESSUPRIMENTO"
            ],
            "STATUS VALIDADO": [
                "SALDO ZERO",
                null,
                "SUJEIRA",
                null,
                null,
                "SEPARAÇÃO (var)",
                "SUJEIRA",
                null,
                "DECANTING",
                "MOVIMENTAÇÃO",
                "SUJEIRA",
                "RESSUPRIMENTO",
                "SUJEIRA (var)",
                "DECANTING",
                "HOLDING (var)",
                "DROP'S",
                "MOVIMENTAÇÃO",
                null,
                "SEPARAÇÃO",
                "SUJEIRA",
                null,
                "SEPARAÇÃO",
                null,
                null,
                null,
                null,
                null,
                null,
                "SUJEIRA",
                null
            ],
            "SALDO ATIVO": [
                0.0,
                100.56,
                189.32,
                330.4,
                0.0,
                2794.43,
                50.16,
                61.78,
                1.1,
                242.14,
                334.53,
                245.15,
                8.11,
                29.43,
                7.25,
                51.18,
                65.94,
                1.15,
                61.78,
                29.37,
                34.68,
                199.61,
                14.94,
                40.61,
                7.14,
                5.39,
                0.71,
                6.58,
                9.89,
                44.13
            ],
            "QUEM VALIDOU": [
                "ESCANEAMENTO",
                "SEM VALIDAÇÃO",
                "TAINA (var)",
                "SEM VALIDAÇÃO",
                "SEM VALIDAÇÃO (var)",
                "Maria",
                "PAULA",
                "SEM VALIDAÇÃO",
                "Luiz",
                "Luiz",
                "TAINA",
                "TAINA",
                "PAULA",
                "Luiz",
                "PAULA",
                "PAULA",
                "TAINA",
                "SEM VALIDAÇÃO",
                "Luiz",
                "Luiz",
                "SEM VALIDAÇÃO",
                "Maria",
                "SEM VALIDAÇÃO",
                "SEM VALIDAÇÃO",
                "SEM VALIDAÇÃO",
                "SEM VALIDAÇÃO",
                "SEM VALIDAÇÃO",
                "SEM VALIDAÇÃO",
                "PAULA",
                "SEM VALIDAÇÃO"
            ],
            "DIAS RECORRENTE": [
                11.93,
                1.49,
                0.0,
                6.08,
                1.23,
                11.58,
                10.11,
                4.63,
                2.79,
                8.77,
                3.21,
                3.8,
                8.66,
                1.87,
                7.72,
                5.42,
                9.41,
                6.5,
                3.33,
                4.97,
                6.61,
                9.16,
                6.61,
                1.9,
                10.3,
                1.61,
                7.15,
                4.22,
                8.08,
                3.52
            ],
            "NAT ACUMULADO SKU": [
                130.02,
                8.38,
                0.0,
                20.24,
                1.06,
                244.07,
                50.12,
                5.81,
                35.12,
                71.82,
                7.61,
                12.29,
                49.29,
                4.96,
                10.66,
                53.13,
                79.43,
                16.06,
                24.69,
                36.3,
                77.34,
                70.58,
                44.98,
                2.07,
                75.09,
                2.43,
                33.61,
                150.57,
                23.58,
                43.32
            ]
        },
        "SEPARAÇÃO": {
            "SKU": [
                15542.65,
                100204.93,
                41698.62,
                83606.64,
                48672.21,
                98895.11,
                531.34,
                8921.5,
                42636.48,
                27474.34,
                33237.4,
                271668.71,
                1308058.25,
                67178.9,
                17957.01,
                73409.66,
                104756.23,
                34477.08,
                680321.28,
                8420.13,
                1029385.75,
                21607.72,
                51278.51,
                92005.99,
                78598.06,
                22809.17,
                223454.85,
                115629.41,
                37229.45,
                674.44
            ],
            "DESCRIÇÃO": [
                "XULTOPHY 3ML 1 APLIC (var)",
                "PREDSIM 20MG 20'S",
                "FIASP FLEXTOU 100U 3ML (var)",
                "SBP REP SUAV REF+50%SG",
                "NORIPURUM EV END 5X5ML",
                "REACH FIO D MENT 50",
                "BETADINE XR 48MG 30'S",
                "LANTUS SOLOSTAR 3ML",
                "MIOSAN 5MG 30'S",
                "*RISPERID 3 EUG30'S",
                "BB CR BASE MEDIA 30ML",
                "GILLETTE FUSION5 C/4UN",
                "*DIVALCON ER 500MG 60S",
                "ICACORT CREME 30GR",
                "*FLUOXET 20 TEG 30S-C1",
                "ADVIL EXTR ALIVIO 20'S (var)",
                "NEOSALDINA 15ML GTA",
                "CELESTAMINE S/AC 120ML",
                "STILGRIP 1X5G",
                "DOVE DES MEN+CAR INVIS",
                "NEEDS ESP IMP BG 1,2X3",
                "LIDOCAINA 50MG PBG 25G (var)",
                "VALDA FRIE CANELA 25G",
                "PANTOPRAZOL 40MEG 14'S",
                "RISQUE GEL CREM LOOK F",
                "OSCILLOC 200K C/6",
                "ENGOV AFTER P.LIMON250",
                "AMOX BIG 500MG 30'S",
                "LASTACAFT 0,25 3ML",
                "NEOLEFRIN 20'S"
            ],
            "SETOR": [
                "D (var)",
                "G",
                "W",
                "V",
                "H",
                "M (var)",
                "V",
                "A",
                "G",
                "V",
                "G",
                "M",
                "H",
                "M",
                "X",
                "H",
                "V",
                "M",
                "M",
                "A",
                "L",
                "Y",
                "A",
                "G",
                "Y",
                "M (var)",
                "N",
                "M (var)",
                "J",
                "M"
            ],
            "ENDEREÇO": [
                "5-D-07-013-03",
                "6-G-01-006-03",
                "6-W-09-005-03",
                "7-V-19-019-05",
                "7-H-13-001-04",
                "7-M-18-022-03",
                "7-V-01-011-01",
                "6-A-06-011-03",
                "6-G-01-002-04",
                "7-V-32-021-03 (var)",
                "6-G-01-005-02",
                "7-M-14-019-06",
                "7-H-03-018-01",
                "7-M-31-006-01 (var)",
                "6-X-03-026-03",
                "7-H-13-024-04",
                "7-V-01-016-01",
                "7-M-31-017-01",
                "7-M-19-013-06 (var)",
                "6-A-06-006-03",
                "5-L-03-024-01",
                "7-Y-30-014-01",
                "6-A-11-003-01 (var)",
                "6-G-01-001-02",
                "7-Y-03-005-03",
                "7-M-05-005-02",
                "6-N-06-004-01",
                "7-M-17-018-04",
                "6-J-01-005-02",
                "7-M-09-003-03 (var)"
            ],
            "SUGESTÃO TOTAL": [
                386.35,
                409.15,
                181.18,
                126.19,
                198.49,
                110.41,
                109.44,
                75.58,
                307.92,
                92.94,
                240.48,
                104.14,
                59.74,
                140.01,
                74.5,
                78.57,
                62.03,
                118.93,
                93.02,
                62.02,
                55.63,
                91.98,
                71.02,
                235.76,
                121.04,
                122.73,
                128.86,
                54.04,
                797.98,
                49.34
            ],
            "UNID. FATURADAS": [
                0.0,
                264.3,
                0.0,
                0.0,
                132.17,
                17.53,
                27.31,
                0.0,
                97.29,
                0.0,
                106.51,
                15.43,
                0.0,
                46.67,
                0.0,
                0.0,
                0.0,
                55.16,
                23.77,
                0.0,
                0.0,
                0.0,
                0.0,
                78.59,
                0.0,
                82.92,
                123.16,
                3.6,
                592.63,
                0.0
            ],
            "UNID. NAT": [
                88.97,
                87.59,
                58.92,
                51.69,
                78.1,
                66.35,
                61.81,
                81.64,
                77.36,
                62.3,
                80.34,
                83.23,
                65.93,
                51.77,
                52.34,
                78.13,
                48.41,
                43.67,
                62.48,
                61.43,
                126.41,
                46.14,
                64.48,
                91.22,
                53.57,
                186.28,
                44.9,
                99.06,
                46.75,
                77.38
            ],
            "SALDO INICIAL": [
                865.74,
                8431.14,
                582.84,
                107.93,
                500.18,
                152.96,
                542.01,
                1317.45,
                9383.41,
                629.64,
                6104.19,
                212.32,
                155.37,
                113.63,
                119.9,
                110.28,
                139.34,
                200.5,
                97.27,
                386.38,
                67.41,
                190.73,
                368.7,
                6025.04,
                265.31,
                705.03,
                418.48,
                129.66,
                601.91,
                221.13
            ],
            "SALDO CASE": [
                0.0,
                0.0,
                0.0,
                17.45,
                587.91,
                166.11,
                37.03,
                0.0,
                0.0,
                0.0,
                0.0,
                412.87,
                0.0,
                0.0,
                0.0,
                106.57,
                185.41,
                0.0,
                197.83,
                0.0,
                0.0,
                141.56,
                0.0,
                0.0,
                967.27,
                0.0,
                0.0,
                0.0,
                0.0,
                59.04
            ],
            "STATUS NÃO ATENDIMENTO": [
                "SEPARAÇÃO",
                "SEPARAÇÃO",
                "SEPARAÇÃO",
                "SEPARAÇÃO",
                "SEPARAÇÃO",
                "SEPARAÇÃO",
                "SEPARAÇÃO",
                "SEPARAÇÃO",
                "SEPARAÇÃO",
                "SEPARAÇÃO",
                "SEPARAÇÃO",
                "SEPARAÇÃO",
                "SEPARAÇÃO",
                "SEPARAÇÃO",
                "SEPARAÇÃO",
                "SEPARAÇÃO",
                "SEPARAÇÃO",
                "SEPARAÇÃO",
                "SEPARAÇÃO",
                "SEPARAÇÃO (var)",
                "SEPARAÇÃO",
                "SEPARAÇÃO (var)",
                "SEPARAÇÃO",
                "SEPARAÇÃO (var)",
                "SEPARAÇÃO",
                "SEPARAÇÃO",
                "SEPARAÇÃO",
                "SEPARAÇÃO",
                "SEPARAÇÃO",
                "SEPARAÇÃO"
            ],
            "STATUS VALIDADO": [
                "SALDO ZERO (var)",
                null,
                null,
                null,
                null,
                "SUJEIRA",
                null,
                "SUJEIRA",
                "SUJEIRA",
                "OVER",
                null,
                "SUJEIRA",
                "SUJEIRA",
                null,
                null,
                "SUJEIRA",
                "SUJEIRA",
                "SUJEIRA",
                "SUJEIRA",
                "SUJEIRA",
                "SUJEIRA",
                "SUJEIRA (var)",
                null,
                "SUJEIRA",
                null,
                null,
                null,
                null,
                "VENCIDO",
                "SUJEIRA"
            ],
            "SALDO ATIVO": [
                307.11,
                6082.09,
                424.61,
                119.03,
                115.88,
                19.51,
                41.15,
                1681.75,
                12373.44,
                186.56,
                3620.54,
                219.56,
                209.61,
                44.75,
                204.59,
                40.09,
                108.58,
                78.42,
                61.02,
                154.55,
                56.16,
                145.18,
                180.48,
                3865.08,
                281.49,
                772.41,
                349.41,
                27.06,
                359.63,
                20.06
            ],
            "QUEM VALIDOU": [
                "Luiz",
                "Luciana",
                "SEM VALIDAÇÃO",
                "SEM VALIDAÇÃO",
                "SEM VALIDAÇÃO",
                "GABRIEL",
                "CAIQUE",
                "CAIQUE",
                "SEM VALIDAÇÃO",
                "TAINA",
                "SEM VALIDAÇÃO",
                "SEM VALIDAÇÃO",
                "REGIANE (var)",
                "PAULA JULIÃO",
                "ESCANEAMENTO",
                "CAIQUE",
                "SEM VALIDAÇÃO",
                "SEM VALIDAÇÃO",
                "SEM VALIDAÇÃO",
                "DEBORA",
                "SEM VALIDAÇÃO",
                "Luiz",
                "PAULA",
                "PAULA JULIÃO",
                "SEM VALIDAÇÃO",
                "SEM VALIDAÇÃO (var)",
                "TAINA",
                "SEM VALIDAÇÃO (var)",
                "dennis",
                "TAINA"
            ],
            "DIAS RECORRENTE": [
                11.35,
                1.15,
                0.0,
                5.93,
                10.87,
                12.93,
                7.21,
                8.76,
                0.0,
                6.69,
                0.0,
                9.19,
                0.72,
                8.66,
                2.52,
                8.68,
                8.24,
                10.58,
                12.01,
                8.74,
                0.0,
                8.22,
                5.72,
                0.79,
                7.48,
                12.25,
                7.81,
                8.85,
                0.0,
                7.62
            ],
            "NAT ACUMULADO SKU": [
                41.74,
                2.49,
                0.0,
                6.8,
                273.58,
                21.41,
                14.3,
                24.83,
                0.0,
                132.01,
                0.0,
                445.82,
                322.9,
                13.02,
                6.91,
                46.39,
                29.96,
                14.42,
                94.49,
                15.69,
                0.0,
                192.64,
                75.56,
                1.01,
                32.27,
                31.55,
                29.41,
                22.11,
                0.0,
                56.28
            ]
        }
    }
}